Workbook

Sheet Summary
A1: HO 42 extraction log - summary
A3: Count by event type
A4: Event type | B4: Rows
A5: Request for troops | B5: =COUNTIF(Events!$C$2:$C$1000,A5) -> 43
A6: Corps founded | B6: =COUNTIF(Events!$C$2:$C$1000,A6) -> 8
A7: Corps armed/expanded | B7: =COUNTIF(Events!$C$2:$C$1000,A7) -> 7
A8: Barracks | B8: =COUNTIF(Events!$C$2:$C$1000,A8) -> 9
A9: Corps forming (context) | B9: =COUNTIF(Events!$C$2:$C$1000,A9) -> 1
A10: Other | B10: =COUNTIF(Events!$C$2:$C$1000,A10) -> 4
A11: TOTAL | B11: =SUM(B5:B10) -> 72
A13: Requests for troops by kind
A14: Request kind | B14: Rows
A15: Actual | B15: =COUNTIFS(Events!$C$2:$C$1000,"Request for troops",Events!$Y$2:$Y$1000,A15) -> 17
A16: Pre-emptive | B16: =COUNTIFS(Events!$C$2:$C$1000,"Request for troops",Events!$Y$2:$Y$1000,A16) -> 17
A17: Contingent | B17: =COUNTIFS(Events!$C$2:$C$1000,"Request for troops",Events!$Y$2:$Y$1000,A17) -> 4
A18: Report only | B18: =COUNTIFS(Events!$C$2:$C$1000,"Request for troops",Events!$Y$2:$Y$1000,A18) -> 5
A19: TOTAL | B19: =SUM(B15:B18) -> 43
A21: By year
A22: Year | B22: Rows
A23: 1789 | B23: =COUNTIF(Events!$P$2:$P$1000,A23) -> 0
A24: 1790 | B24: =COUNTIF(Events!$P$2:$P$1000,A24) -> 2
A25: 1791 | B25: =COUNTIF(Events!$P$2:$P$1000,A25) -> 10
A26: 1792 | B26: =COUNTIF(Events!$P$2:$P$1000,A26) -> 24
A27: 1793 | B27: =COUNTIF(Events!$P$2:$P$1000,A27) -> 2
A28: 1794 | B28: =COUNTIF(Events!$P$2:$P$1000,A28) -> 11
A29: 1795 | B29: =COUNTIF(Events!$P$2:$P$1000,A29) -> 23
A30: 1796 | B30: =COUNTIF(Events!$P$2:$P$1000,A30) -> 0
A31: 1797 | B31: =COUNTIF(Events!$P$2:$P$1000,A31) -> 0
A32: 1798 | B32: =COUNTIF(Events!$P$2:$P$1000,A32) -> 0
A33: 1799 | B33: =COUNTIF(Events!$P$2:$P$1000,A33) -> 0
A34: 1800 | B34: =COUNTIF(Events!$P$2:$P$1000,A34) -> 0
A35: 1801 | B35: =COUNTIF(Events!$P$2:$P$1000,A35) -> 0
A36: TOTAL | B36: =SUM(B23:B35) -> 72
A38: Distinct episodes (all rows) | B38: =SUMPRODUCT((Events!$B$2:$B$1000<>"")/COUNTIF(Events!$B$2:$B$1000,Events!$B$2:$B$1000&"")) -> 61
A39: Rows still to check (Folio basis = Unclear) | B39: =COUNTIF(Events!$I$2:$I$1000,"Unclear - check") -> 18

Sheet Events
A1: Row ID | B1: Episode ID | C1: Event type | D1: Key quote? | E1: Call number | F1: File | G1: PDF page no. | H1: Folio | I1: Folio basis | J1: Link to PDF/Photos | K1: Image status | L1: Transcription status | M1: Transcribed text (key quote) | N1: Date (as written) | O1: Date (ISO) | P1: Year | Q1: Location (as written) | R1: Place (normalised) | S1: County | T1: Writer | U1: Writer role | V1: Addressed to | W1: Home Secretary in office | X1: Disturbance type | Y1: Request kind | Z1: Civil power inadequate? | AA1: Force requested (type & size) | AB1: Military already nearby? | AC1: Response text (if given) | AD1: Outcome | AE1: Response date | AF1: Response location | AG1: Response writer | AH1: Response source | AI1: Notes / flag
A2: HO42-0001 | B2: E01 | C2: Request for troops | D2: N | E2: HO 42/16 | F2: HO-42-16_01.pdf | H2: ff.58, 60, 61 | I2: Unclear - check | K2: Digitised (TNA PDF) | L2: Key quote only | M2: "...should arise any Necessity for the Interference of the Military, it would be expedient for me to know the nearest Place to this Spot where Troops are now station'd... from the War Office, with the Name of the commanding Officer." | N2: 17 Mar 1790 | O2: 1790-03-17 | P2: =IF(O2="","",VALUE(LEFT(O2,4))) -> 1790 | Q2: Keynsham (nr Bristol) | R2: Keynsham | S2: Somerset | T2: Thomas Ireland, magistrate | U2: Magistrate / JP | W2: =IF(O2="","",INDEX(Lookups!$B$2:$B$20,MATCH(O2,Lookups!$A$2:$A$20,1))) -> Grenville | X2: Anti-machinery | Y2: Contingent | Z2: N | AA2: None yet - asks location of nearest troops + CO name | AB2: Unclear | AD2: Not needed | AI2: Anti-machinery/colliers riot vs newly introduced woollen manufactory machines; contingent request for nearest garrison; Ireland preferred civil power. | Outcome (orig.): Not called (dispersed by Riot Act)
A3: HO42-0002 | B3: E02 | C3: Request for troops | D3: N | E3: HO 42/16 | F3: HO-42-16_05.pdf | H3: ff.317-319 | I3: Unclear - check | K3: Digitised (TNA PDF) | L3: Key quote only | M3: "...we cannot depend or expect much support from our Constables... to request such support for our Persons & property as the nature of the case requires." / Mulgrave: "the object... is to have some military force quartered in the Town at the time of the Election." | N3: 1 Sep 1790 (fwd 6 Sep) | O3: 1790-09-01 | P3: =IF(O3="","",VALUE(LEFT(O3,4))) -> 1790 | Q3: Scarborough | R3: Scarborough | S3: Yorkshire (N. Riding) | T3: Jno Harrison & Jno Woodall, bailiffs; fwd by Henry Phipps (Ld Mulgrave) | U3: Mayor / corporation | V3: Ld Mulgrave, fwd to Grenville | W3: =IF(O3="","",INDEX(Lookups!$B$2:$B$20,MATCH(O3,Lookups!$A$2:$A$20,1))) -> Grenville | X3: Election | Y3: Pre-emptive | Z3: Y | AA3: Military force quartered in town during election | AB3: Unclear | AD3: Forwarded | AI3: Corporation vs freemen threatening to seize control by force at the election; constables unreliable. | Outcome (orig.): Forwarded to Grenville; outcome not in file
A4: HO42-0003 | B4: E03 | C4: Request for troops | D4: N | E4: HO 42/34 | F4: HO-42-34_01.pdf | H4: ff.55-56 | I4: Unclear - check | K4: Digitised (TNA PDF) | L4: Key quote only | M4: "...pull down the mill & destroy the corn & flour therein, situated in the parish of Lamberhurst, belonging to Messrs Webb & Fowle..." | N4: 23 Jan 1795 | O4: 1795-01-23 | P4: =IF(O4="","",VALUE(LEFT(O4,4))) -> 1795 | Q4: Lamberhurst | R4: Lamberhurst | S4: Kent | T4: Charles Jaques, magistrate (for Fowle, mill-owner) | U4: Magistrate / JP | W4: =IF(O4="","",INDEX(Lookups!$B$2:$B$20,MATCH(O4,Lookups!$A$2:$A$20,1))) -> Portland | X4: Food / provisions | Y4: Pre-emptive | Z4: Unclear | AA4: Not specified | AB4: Unclear | AC4: Docket: "Copy of this sent to Ld Amherst Jany 24 with his Grace's opinion that a small number of troops shd be ordered to Lamberhurst to aid the magistrates if necessary." | AD4: Approved | AE4: 24 Jan 1795 | AF4: Whitehall | AG4: Portland -> Amherst | AH4: HO 42 docket | AI4: Flour-mill riot; GRANTED (small number of troops ordered). Clean request+response pair. | Outcome (orig.): Approved
A5: HO42-0004 | B5: E04 | C5: Corps founded | D5: Y | E5: HO 42/34 | F5: HO-42-34_02.pdf | H5: ff.117-118, 122-123 | I5: Unclear - check | K5: Digitised (TNA PDF) | L5: Key quote; full text held | M5: "...expedient to augment the domestic Force of this Country, as well to resist any hostile Attempts... as to suppress any Insurrections... the Object of their arming is, to aid the civil Magistracy." | N5: 28 Jan 1795 (fwd 21 & 26 Feb) | O5: 1795-01-28 | P5: =IF(O5="","",VALUE(LEFT(O5,4))) -> 1795 | Q5: Newcastle upon Tyne | R5: Newcastle upon Tyne | S5: Northumberland | T5: Mayor Francis Johnson; fwd Duke of Northumberland (Ld Lieut) | U5: Mayor / corporation | V5: Duke of Northumberland (Ld Lieut), fwd to HO | W5: =IF(O5="","",INDEX(Lookups!$B$2:$B$20,MATCH(O5,Lookups!$A$2:$A$20,1))) -> Portland | X5: Preventive / general | AC5: His Majesty accepted the offer to form a Volunteer Corps of Infantry for the internal defence of the town; Northumberland protests the loose, self-governing terms. | AD5: Approved | AE5: 26 Feb 1795 | AG5: King via Portland | AH5: Other | AI5: KEY QUOTE. Volunteer infantry corps; full text held. Lord-Lieutenant ambivalence on record. | Outcome (orig.): Approved
A6: HO42-0005 | B6: E05 | C6: Corps armed/expanded | D6: N | E6: HO 42/34 | F6: HO-42-34_03.pdf | H6: ff.186-188 | I6: Unclear - check | K6: Digitised (TNA PDF) | L6: Key quote only | M6: "...I request the favor of Government arming me with forty stand of Small Arms with necessary Accoutrements... & a couple of barrels of ball Cartridges... I cannot but again repeat my former application for a couple of field pieces to be attached to this Company..." | N6: 11 Mar 1795 | O6: 1795-03-11 | P6: =IF(O6="","",VALUE(LEFT(O6,4))) -> 1795 | Q6: Penzance | R6: Penzance | S6: Cornwall | T6: Capt Tremenheere, Penzance Volunteer Company | U6: Volunteer / militia officer | W6: =IF(O6="","",INDEX(Lookups!$B$2:$B$20,MATCH(O6,Lookups!$A$2:$A$20,1))) -> Portland | X6: Other / unclear | AB6: Volunteers only | AI6: Miners' rising dispersed by bayonet/Riot Act; corps deployed with improvised cannon; 20-30 enrolling as 'Penzance Artillery Men'. | CHECK: Disturbance type: 1795 Cornish miners' risings were largely over grain prices - confirm from letters and recode.
A7: HO42-0006 | B7: E05 | C7: Corps armed/expanded | D7: N | E7: HO 42/34 | F7: HO-42-34_03.pdf | H7: ff.199-200 | I7: Unclear - check | K7: Digitised (TNA PDF) | L7: Key quote only | M7: "There being no other Military force at this place but the Volunteer Company, I have thought proper to keep them in constant readiness, which produces an Expence which there is no fund to supply. I therefore request your Grace's directions herein." | N7: 14 Mar 1795 | O7: 1795-03-14 | P7: =IF(O7="","",VALUE(LEFT(O7,4))) -> 1795 | Q7: Penzance | R7: Penzance | S7: Cornwall | T7: Capt Tremenheere | U7: Volunteer / militia officer | W7: =IF(O7="","",INDEX(Lookups!$B$2:$B$20,MATCH(O7,Lookups!$A$2:$A$20,1))) -> Portland | X7: Other / unclear | AB7: Volunteers only | AI7: Funding/authority request tied to keeping the corps mobilised.
A8: HO42-0007 | B8: E05 | C8: Corps armed/expanded | D8: N | E8: HO 42/34 | F8: HO-42-34_03.pdf | H8: f.201 | I8: Unclear - check | K8: Digitised (TNA PDF) | L8: Key quote only | M8: "...humbly beg leave to support the application made to Government by Captain Tremenheere for two field pieces to be attached to his Company." | N8: 14 Mar 1795 | O8: 1795-03-14 | P8: =IF(O8="","",VALUE(LEFT(O8,4))) -> 1795 | Q8: Penzance | R8: Penzance | S8: Cornwall | T8: Mayor & Justices of Penzance (Board, Batten) | U8: Mayor / corporation | W8: =IF(O8="","",INDEX(Lookups!$B$2:$B$20,MATCH(O8,Lookups!$A$2:$A$20,1))) -> Portland | X8: Other / unclear | AB8: Volunteers only | AI8: Corporation endorsement of the arms request.
A9: HO42-0008 | B9: E05 | C9: Request for troops | D9: N | E9: HO 42/34 | F9: HO-42-34_03.pdf | H9: f.210 | I9: Unclear - check | K9: Digitised (TNA PDF) | L9: Key quote only | M9: "...induce us to request Your Lordship to order such regular forces or Militia as may be thought necessary to be sent into this Neighbourhood as speedily as possible in support of the Civil power and in Aid of the Volunteer Companies." PS: "Two companies may with ease be accommodated..." | N9: 16 Mar 1795 | O9: 1795-03-16 | P9: =IF(O9="","",VALUE(LEFT(O9,4))) -> 1795 | Q9: Penzance, Cornwall | R9: Penzance | S9: Cornwall | T9: Wm Borlase, John Price, Thos Pascoe, Richd Hichens (JPs) + Collector of Customs | U9: Magistrate / JP | W9: =IF(O9="","",INDEX(Lookups!$B$2:$B$20,MATCH(O9,Lookups!$A$2:$A$20,1))) -> Portland | X9: Other / unclear | Y9: Actual | Z9: Y | AA9: Regular forces or militia; "two companies may with ease be accommodated" | AB9: Volunteers only | AI9: Formal county-JP request for regulars/militia after Volunteer Companies alone proved insufficient.
A10: HO42-0009 | B10: E06 | C10: Corps armed/expanded | D10: N | E10: HO 42/34 | F10: HO-42-34_01.pdf | H10: ff.9-10 | I10: Unclear - check | K10: Digitised (TNA PDF) | L10: Key quote only | M10: Offer to raise two additional troops (100 men) for his Fencible Regiment; notes Government had declined the expense of purchasing horses. | N10: 4 Jan 1795 | O10: 1795-01-04 | P10: =IF(O10="","",VALUE(LEFT(O10,4))) -> 1795 | Q10: Exeter (Heavitree Barracks) | R10: Exeter | S10: Devon | T10: Montagu Burgoyne | U10: Military officer | W10: =IF(O10="","",INDEX(Lookups!$B$2:$B$20,MATCH(O10,Lookups!$A$2:$A$20,1))) -> Portland | AI10: Officer's offer to expand a fencible corps; fiscal-military bargaining over horse cost.
A11: HO42-0010 | B11: E07 | C11: Corps founded | D11: Y | E11: HO 42/30 | F11: HO-42-30_01.pdf | H11: ff.21-24 | I11: Unclear - check | K11: Digitised (TNA PDF) | L11: Key quote; full text held | M11: "...do without Delay quit the Field of Argument for that of Arms... forming themselves into a Military Association... be formed into Companies of Infantry, but to offer the Service of as many Cavalry as can be mustered... to repel external Violence, suppress internal Commotions..." | N11: 6 May 1794 (res. 24 Mar & 19 Apr) | O11: 1794-05-06 | P11: =IF(O11="","",VALUE(LEFT(O11,4))) -> 1794 | Q11: Birmingham | R11: Birmingham | S11: Warwickshire | T11: John Brooke / J. Morfitt (Loyal True Blues) | U11: Loyalist association | W11: =IF(O11="","",INDEX(Lookups!$B$2:$B$20,MATCH(O11,Lookups!$A$2:$A$20,1))) -> Dundas | X11: Preventive / general | AI11: KEY QUOTE. Loyalist association militarising into infantry+cavalry; ~50-100 enrolled; full text held.
A12: HO42-0011 | B12: E08 | C12: Corps founded | D12: Y | E12: HO 42/30 | F12: HO-42-30_01.pdf | H12: ff.52-53 | I12: Unclear - check | K12: Digitised (TNA PDF) | L12: Key quote only | M12: "...do hereby engage to form ourselves into a military Corps, under the Sanction of Government, to be called the Independent Sheffield Volunteers... in preventing or suppressing all riotous, disorderly & unlawful meetings or assemblies." | N12: 1 May 1794 (fwd 12 May) | O12: 1794-05-01 | P12: =IF(O12="","",VALUE(LEFT(O12,4))) -> 1794 | Q12: Sheffield | R12: Sheffield | S12: Yorkshire (W. Riding) | T12: J. Russell, Dronfield | U12: Loyalist association | W12: =IF(O12="","",INDEX(Lookups!$B$2:$B$20,MATCH(O12,Lookups!$A$2:$A$20,1))) -> Dundas | X12: Preventive / general | AI12: KEY QUOTE. Corps raised in a radical town; 100+ signatures; engagement text held.
A13: HO42-0012 | B13: E09 | C13: Barracks | D13: Y | E13: HO 42/30 | F13: HO-42-30_01.pdf | H13: ff.62-63 | I13: Unclear - check | K13: Digitised (TNA PDF) | L13: Key quote only | M13: "...particularly in case of Riots and Disturbances among the Pitmen and others employed in the Coalworks... the peace... most effectually preserved by the appearance of Cavalry on the Spot ready to assist the civil Power." | N13: 12 May 1794 | O13: 1794-05-12 | P13: =IF(O13="","",VALUE(LEFT(O13,4))) -> 1794 | Q13: Newcastle upon Tyne | R13: Newcastle upon Tyne | S13: Northumberland | T13: Mayor Wm Yielder & corporation | U13: Mayor / corporation | W13: =IF(O13="","",INDEX(Lookups!$B$2:$B$20,MATCH(O13,Lookups!$A$2:$A$20,1))) -> Dundas | X13: Labour / industrial | Y13: Pre-emptive | AA13: Cavalry barracks | AB13: Unclear | AI13: Request to build cavalry barracks, explicitly riot-driven (pitmen).
A14: HO42-0013 | B14: E10 | C14: Barracks | D14: N | E14: HO 42/30 | F14: HO-42-30_01.pdf | H14: ff.16-17 | I14: Unclear - check | K14: Digitised (TNA PDF) | L14: Key quote only | M14: Objection to the siting of proposed barracks at Wells ('a mere Village, free from seditious Societies'). | N14: 5 May 1794 | O14: 1794-05-05 | P14: =IF(O14="","",VALUE(LEFT(O14,4))) -> 1794 | Q14: Wells | R14: Wells | S14: Somerset | T14: Mr Tudway | U14: Private individual | W14: =IF(O14="","",INDEX(Lookups!$B$2:$B$20,MATCH(O14,Lookups!$A$2:$A$20,1))) -> Dundas | X14: Preventive / general | AI14: Marginal - about siting, not raising. Included for completeness. | CHECK: Barracks row is an OBJECTION to siting, not a request - consider separate event type.
A15: HO42-0014 | B15: E11 | C15: Request for troops | D15: N | E15: HO 42/33 | F15: HO-42-33_01.pdf | H15: ~f.43-44 (also narr. ff.220-225 in _03) | I15: Unclear - check | K15: Digitised (TNA PDF) | L15: Key quote only | M15: "...finding the impossibility of quelling a further riot with the civil power only... I am therefore going to send to the Tower for 100 of His Majesty's Guards, and... I shall stand in Need of further military Aid at Night." (also asked Light Horse Volunteers & HAC) | N15: 20-22 Aug 1794 | O15: 1794-08-20 | P15: =IF(O15="","",VALUE(LEFT(O15,4))) -> 1794 | Q15: London | R15: London | S15: Middlesex / City | T15: Lord Mayor (Paul Le Mesurier) | U15: Mayor / corporation | V15: Tower (Guards); HAC; Light Horse Volunteers | W15: =IF(O15="","",INDEX(Lookups!$B$2:$B$20,MATCH(O15,Lookups!$A$2:$A$20,1))) -> Portland | X15: Recruitment / crimping | Y15: Actual | Z15: Y | AA15: 100 Guards from Tower + Light Horse Volunteers & HAC | AB15: Y | AI15: London 'crimp' riots; civil magistrate requesting Guards + volunteer corps. Core request; full transcription pending. | Follow-up in HO 42/33 ff.236-237 (23 Aug 1794): Lord Mayor stands down the Guards but asks the Deputy Governor of the Tower to keep "a strong Picquet of at least Sixty Men ready to come to me on the shortest Notice"; LHV 12-15 men on duty nightly, ~50 Artillery Co.; "if the Rioters should begin again I shall immediately send to the Tower for the Guards". Also ff.240-1 Colquhoun: nearly 500 special constables, LHV & Hackney Association marched to Finsbury Square.
A16: HO42-0015 | B16: E11 | C16: Corps forming (context) | D16: N | E16: HO 42/33 | F16: HO-42-33_03.pdf | H16: ff.160, 162-163 | I16: Unclear - check | K16: Digitised (TNA PDF) | L16: Key quote only | M16: "the Armed Associations which are forming in this quarter of the Metropolis cannot be ready to act for a considerable length of time..." / "none of the Military associations which have been forming in Hackney and the Town Hamlets are yet in a situation to act." | N16: 21 Aug 1794 | O16: 1794-08-21 | P16: =IF(O16="","",VALUE(LEFT(O16,4))) -> 1794 | Q16: London (Hackney, Tower Hamlets) | R16: London | S16: Middlesex | T16: Patrick Colquhoun, Worship Street | U16: Magistrate / JP | W16: =IF(O16="","",INDEX(Lookups!$B$2:$B$20,MATCH(O16,Lookups!$A$2:$A$20,1))) -> Portland | AI16: Evidence of armed associations being raised across metropolitan parishes (context, not a discrete offer).
A17: HO42-0016 | B17: E12 | C17: Corps armed/expanded | D17: N | E17: HO 42/30 | F17: HO-42-30_04.pdf | H17: ff.270-271 | I17: Unclear - check | K17: Digitised (TNA PDF) | L17: Key quote only | M17: "His Majesty having been pleased to approve of the Steps taken in the Isle of Wight to augment by voluntary subscription the internal force of it, and particularly by an increase of the Militia... to apply for two Field Pieces of Cannon to be attached to this Corps. It is proposed that the embodied Company of the Militia shd be trained to the use of the Guns..." | N17: 24 May 1794 | O17: 1794-05-24 | P17: =IF(O17="","",VALUE(LEFT(O17,4))) -> 1794 | Q17: Isle of Wight | R17: Isle of Wight | S17: Hampshire | T17: Thomas Orde (Governor of the Isle of Wight) | U17: Other official | W17: =IF(O17="","",INDEX(Lookups!$B$2:$B$20,MATCH(O17,Lookups!$A$2:$A$20,1))) -> Dundas | X17: Preventive / general | AC17: Militia augmentation already approved by the King; the field-pieces request's outcome not in this file. | AD17: Approved | AH17: Other | AI17: Militia increase by voluntary subscription + request for 2 field pieces; internal-defence framed. Key-quote adjacent (militia augmentation). | Outcome (orig.): (augmentation approved) | CHECK: Key-quote adjacent (militia augmentation).
A18: HO42-0017 | B18: E13 | C18: Request for troops | D18: N | E18: HO 42/33 | F18: HO-42-33_05.pdf | H18: f.377 | I18: Unclear - check | K18: Digitised (TNA PDF) | L18: Key quote only | M18: "This Morning I gave orders for Two hundred extra Constables, & I have also wrote to the Artillery Company & to the Light Horse Volunteers who are and have been in readiness for several hours to co-operate with the Civil Power should occasion require. I have reason to believe the Peace of the City will be preserved." | N18: 22 Nov 1794 | O18: 1794-11-22 | P18: =IF(O18="","",VALUE(LEFT(O18,4))) -> 1794 | Q18: London (Sessions House, Old Bailey) | R18: London | S18: City of London | T18: Lord Mayor of London (Thomas Skinner) | U18: Mayor / corporation | W18: =IF(O18="","",INDEX(Lookups!$B$2:$B$20,MATCH(O18,Lookups!$A$2:$A$20,1))) -> Portland | X18: Radical / political | Y18: Report only | Z18: N | AA18: Artillery Co. & Light Horse Volunteers on standby; 200 extra constables | AB18: Y | AI18: During the Treason Trials (Hardy/Tooke). Civil request to the volunteer corps + 200 extra constables; distinct occasion from the Aug 1794 crimp-riot request. | CHECK: Reclassify? This is a report to HO of local precautions, not a request to government.
A19: HO42-0018 | B19: E14 | C19: Request for troops | D19: N | E19: HO 42/30 | F19: HO-42-30_04.pdf | G19: 30-33 | H19: ff.225, 227 | I19: Folio stamp | K19: Digitised (TNA PDF) | L19: Key quote only | M19: Shuckburgh-Evelyn: "W. Legge of Grosvenor Square called upon me yesterday, expressing much apprehension for himself & neighbours at the unprotected state of the Town of Birmingham by the withdrawing the Cavalry from thence at the present period". Enclosed, Dr Spencer (magistrate): "I hope & trust we shall not be left without one Troop." | N19: 23 May 1794 | O19: 1794-05-23 | P19: =IF(O19="","",VALUE(LEFT(O19,4))) -> 1794 | Q19: Birmingham | R19: Birmingham | S19: Warwickshire | T19: G. Shuckburgh-Evelyn (fwd W. Legge; encl. Dr B. Spencer, magistrate) | U19: MP / peer | V19: Home Office (Nepean?) | W19: =IF(O19="","",INDEX(Lookups!$B$2:$B$20,MATCH(O19,Lookups!$A$2:$A$20,1))) -> Dundas | X19: Radical / political | Y19: Pre-emptive | Z19: Unclear | AA19: Retain at least one troop of cavalry in the town | AB19: Y | AI19: Request to keep cavalry from being withdrawn (regiment under orders for foreign service). Distinct episode from the Loyal True Blues corps (E07). Docket 23 May 1794 "Dom". Addressee inferred - check.
A20: HO42-0019 | B20: E15 | C20: Corps founded | D20: Y | E20: HO 42/30 | F20: HO-42-30_05.pdf | G20: 64-65 | H20: ff.333-334 | I20: Folio stamp | K20: Digitised (TNA PDF) | L20: Key quote only | M20: "...Inclosing to you an account of the late proceedings here, for our internal Defence; not only against our foreign, but, our more to be dreaded, domestic Enemies." | N20: 31 May 1794 | O20: 1794-05-31 | P20: =IF(O20="","",VALUE(LEFT(O20,4))) -> 1794 | Q20: Doncaster | R20: Doncaster | S20: Yorkshire (W. Riding) | T20: Edward Miller | U20: Private individual | V20: Unnamed official (knew his brother & nieces) | W20: =IF(O20="","",INDEX(Lookups!$B$2:$B$20,MATCH(O20,Lookups!$A$2:$A$20,1))) -> Dundas | X20: Radical / political | AI20: KEY QUOTE. Enclosure (account of Doncaster meeting for internal defence) not in this file - check whether a corps or subscription was actually formed; event type provisional. Writer also says his son at Sheffield was "equally alert".
A21: HO42-0020 | B21: E16 | C21: Request for troops | D21: Y | E21: HO 42/33 | F21: HO-42-33_05.pdf | G21: 76-77 | H21: ff.369-370 | I21: Folio stamp | K21: Digitised (TNA PDF) | L21: Key quote only | M21: "Having received this day information that illegal meetings have been held in the town of Kenninghall in this county under a pretence of lowering the price of provisions, and that they have provided to stop waggons and carts loaded with corn, and meal, and have likewise assembled about the bakers shops to seize the bread ... and that they mean to assemble on Monday next at Kenninghall in great numbers - I must request your Grace to order a troop of Horse to be sent immediately to the towns of Harling and Kenninghall to be ready to assist the civil power if necessary." PS: "If the horse are immediately ordered from Norwich they can be at Harling and Kenninghall on Saturday or Sunday." | N21: 4 Dec 1794 | O21: 1794-12-04 | P21: =IF(O21="","",VALUE(LEFT(O21,4))) -> 1794 | Q21: Shadwell Lodge near Thetford (re Kenninghall & Harling) | R21: Kenninghall | S21: Norfolk | T21: Robert John Buxton | U21: MP / peer | V21: Duke of Portland ("My Lord ... your Grace") | W21: =IF(O21="","",INDEX(Lookups!$B$2:$B$21,MATCH(O21,Lookups!$A$2:$A$21,1))) -> Portland | X21: Food / provisions | Y21: Pre-emptive | Z21: Unclear | AA21: One troop of Horse, from Norwich, to Harling and Kenninghall | AB21: N | AI21: Textbook request: food-price assemblies, communication between parishes, troop requested ahead of announced meeting. Writer also calls a general meeting of the principal people of the hundreds at Harling to redress grievances and for "defence of our properties, and the support of the civil power" (possible association - watch for follow-up). Buxton was, I believe, MP for Thetford - verify capacity (MP vs JP). Look for reply in HO 43/6 (Oct 1794-Jul 1795) c. 5-6 Dec 1794.
A22: HO42-0021 | B22: E17 | C22: Request for troops | D22: Y | E22: HO 42/19 | F22: HO-42-19_02.pdf | G22: 31-32, 34 | H22: ff.110-111, 112-113 | I22: Folio stamp | K22: Digitised (TNA PDF) | L22: Key quote only | M22: Under-Sheriff John Brooke, 16 Jul 1791, 7pm: "the attempts which the Magistrates, myself and a numerous party made... proved totally ineffectual. Several Men have lost their lives... nor is there the least gleam of hope that good order can be restored without the aid of a considerable Military Force. Many more Houses are devoted & can only be saved by an early arrival of Troops." Dundas reply to magistrates J. Carles & R. Spencer, 16 Jul (f.112): "I had this morning the honor of receiving your letter of yesterday's date, giving an account of the Riot... I have dispatched a Messenger to Nottingham with directions to the Officer commanding the 15th Dragoons... to send three Troops of that Regiment instantly to Birmingham, to assist the Civil Magistrate". | N22: 15-16 Jul 1791 | O22: 1791-07-15 | P22: =IF(O22="","",VALUE(LEFT(O22,4))) -> 1791 | Q22: Birmingham | R22: Birmingham | S22: Warwickshire | T22: Magistrates J. Carles & R. Spencer (letter of 15 Jul, original not seen); John Brooke, Under-Sheriff of Warwickshire (16 Jul) | U22: Magistrate / JP | V22: Henry Dundas, Home Secretary | W22: =IF(O22="","",INDEX(Lookups!$B$2:$B$22,MATCH(O22,Lookups!$A$2:$A$22,1))) -> Dundas | X22: Radical / political | Y22: Actual | Z22: Y | AA22: "a considerable Military Force" | AB22: N | AC22: Dundas, 16 Jul: 3 troops of 15th Dragoons from Nottingham sent "instantly"; 17 Jul: 3 troops 11th Dragoons from Uxbridge also ordered (f.119), all available force to be collected (f.115 to Lt-Col Churchill). | AD22: Approved | AE22: 1791-07-16 | AF22: Whitehall | AG22: Henry Dundas | AH22: Other | AI22: Priestley ("Church and King") riots, 14-17 Jul 1791. Magistrates' original request of 15 Jul is referred to but not located in 19_01/19_02 - CHECK 19_03. Response source: Home Office draft/copy filed in HO 42. Troop orders 16-23 Jul tabulated at HO 42/19_01 f.70. Also Sam. Garbett to Hawkesbury 16-17 Jul (ff.109, 126): magistrates left town, "the horrible Scene of Plunder continues & no doubt will continue untill Troops arrive."
A23: HO42-0022 | B23: E17 | C23: Request for troops | D23: N | E23: HO 42/19 | F23: HO-42-19_02.pdf | G23: 60 | H23: f.136 | I23: Folio stamp | K23: Digitised (TNA PDF) | L23: Key quote only | M23: "Since sealing the inclosed we think necessary earnestly to intreat a further aid without delay fearing the three Troops may suffer if they come... and we are obliged to require their immediate entrance tho' yet hope they may not be wanted. 20 minutes past 2 o'Clock Sunday Afternoon." | N23: Sunday [17 Jul 1791] | O23: 1791-07-17 | P23: =IF(O23="","",VALUE(LEFT(O23,4))) -> 1791 | Q23: Birmingham | R23: Birmingham | S23: Warwickshire | T23: Birmingham magistrates (unsigned postscript) | U23: Magistrate / JP | V23: Home Office (inferred) | W23: =IF(O23="","",INDEX(Lookups!$B$2:$B$23,MATCH(O23,Lookups!$A$2:$A$23,1))) -> Dundas | X23: Radical / political | Y23: Actual | Z23: Y | AA23: Further aid beyond the three troops | AB23: N | AI23: Follow-up request in same episode. CHECK: writers and addressee inferred (enclosure separated).
A24: HO42-0023 | B24: E18 | C24: Request for troops | D24: N | E24: HO 42/19 | F24: HO-42-19_02.pdf | G24: 53, 80-81, 83-84, 86 | H24: ff.131, 154-155, 157-158, 165 | I24: Folio stamp | K24: Digitised (TNA PDF) | L24: Key quote only | M24: Coventry, 17 Jul 1791 (Town Clerk for Mayor & Justices): "without the aid of military exertions, it is not likely to abate... with little encouragement, numbers may soon be found in Coventry, to engage in similar Outrages". Forwarded by Eardley & John Wilmot (MPs), Bedford Row 18 Jul: Mayor & Justices "desire we will without Delay, apply to you for a Regiment to be quartered there, in order to discourage & suppress all Disposition to disturb the Peace of the City." | N24: 17-18 Jul 1791 | O24: 1791-07-17 | P24: =IF(O24="","",VALUE(LEFT(O24,4))) -> 1791 | Q24: Coventry | R24: Coventry | S24: Warwickshire | T24: Mayor & Justices of Coventry (via Town Clerk); fwd by Eardley & John Wilmot | U24: Mayor / corporation | V24: Henry Dundas (via the city's MPs) | W24: =IF(O24="","",INDEX(Lookups!$B$2:$B$24,MATCH(O24,Lookups!$A$2:$A$24,1))) -> Dundas | X24: Radical / political | Y24: Pre-emptive | Z24: Unclear | AA24: A regiment quartered in the city | AB24: N | AC24: Nepean to Wilmot, 18 Jul (f.155): troops on their march towards Birmingham "will stop at Coventry to assist the Civil Magistrates in quelling any Disturbances that may arise." | AD24: Approved | AE24: 1791-07-18 | AF24: Whitehall | AG24: Evan Nepean | AH24: Other | AI24: Spillover fear from Priestley riots. Route: forwarded by MPs. Writer role of Wilmot/Eardley as MPs - CHECK. | Coventry Town Clerk Edw. Inge, 22 Jul (HO 42/19_03 f.244): Mayor & magistrates thank Govt "for the polite and speedy attention to their request. The appearance of the Military has had the desired effect".
A25: HO42-0024 | B25: E19 | C25: Request for troops | D25: N | E25: HO 42/19 | F25: HO-42-19_03.pdf | G25: 17-18 | H25: ff.178-179 | I25: Folio stamp | K25: Digitised (TNA PDF) | L25: Key quote only | M25: "I am desired by several of the principal Inhabitants, to inform you, a disposition has appeared among the People to riot. By the interposition of the Peace Officers no ill consequences have as yet happened... it may be for the consideration of Government, how far it may be prudent to send a small force. We hear more Troops are coming to Birmingham probably if necessary, One Troop may be spared from thence." | N25: 19 Jul 1791 | O25: 1791-07-19 | P25: =IF(O25="","",VALUE(LEFT(O25,4))) -> 1791 | Q25: Wolverhampton | R25: Wolverhampton | S25: Staffordshire | T25: Wm Beto Taylor | U25: Private individual | V25: Home Office (inferred) | W25: =IF(O25="","",INDEX(Lookups!$B$2:$B$25,MATCH(O25,Lookups!$A$2:$A$25,1))) -> Dundas | X25: Radical / political | Y25: Pre-emptive | Z25: N | AA25: A small force; one troop from Birmingham | AB25: N | AI25: Priestley-riot spillover. CHECK: writer's role (signs for 'principal Inhabitants'; may be a magistrate). Later (19_03 ff.222-226): troop of dragoons stationed at Wolverhampton; Taylor reports magistrates satisfied.
A26: HO42-0025 | B26: E20 | C26: Request for troops | D26: N | E26: HO 42/19 | F26: HO-42-19_03.pdf | G26: 43-44, 82-83 | H26: ff.203-204, 238-239 | I26: Folio stamp | K26: Digitised (TNA PDF) | L26: Key quote only | M26: Mayor John Harris, 21 Jul 1791: transmits anonymous threatening letter; magistrates "feel it their duty after what has happened at Birmingham to transmit the information to Government, submitting to its wisdom the expediency of stationing a competent number of Troops within a day's march of so large a City as Bristol; that in case of any disturbance it may be speedily quelled." Enclosed letter (18 Jul): "Near two 2000 Good Harty hail Strong Ruffins Which will Pull down your fine Manchin houses... Shall Share the Same fate as them at Burmingham". | N26: 21-22 Jul 1791 | O26: 1791-07-21 | P26: =IF(O26="","",VALUE(LEFT(O26,4))) -> 1791 | Q26: Bristol | R26: Bristol | S26: Gloucestershire / Bristol | T26: John Harris, Mayor of Bristol (with Aldermen) | U26: Mayor / corporation | V26: Henry Dundas | W26: =IF(O26="","",INDEX(Lookups!$B$2:$B$26,MATCH(O26,Lookups!$A$2:$A$26,1))) -> Dundas | X26: Radical / political | Y26: Pre-emptive | Z26: N | AA26: A competent number of troops within a day's march | AB26: N | AC26: Govt (Dundas absent) ordered 3rd Regt of Infantry from Reading to Marlborough and Devizes, to proceed to Bristol if the Mayor thinks necessary (Harris to [Home Office], 25 Jul, HO 42/19_04 f.268). Magistrates chose to rely on constables "as no actual tumult has yet taken place". | AD26: Approved | AE26: 1791-07-23 | AH26: Other | AI26: Follow-up 22 Jul (f.238): second anonymous letter, all quiet. Bristol was a county corporate.
A27: HO42-0026 | B27: E21 | C27: Request for troops | D27: N | E27: HO 42/19 | F27: HO-42-19_03.pdf | G27: 90 | H27: f.246 | I27: Folio stamp | K27: Digitised (TNA PDF) | L27: Key quote only | M27: "A Handbill stuck up this morning, on the Churches and several other public Places... together with the murmurs of most of the Manufacturers and Common People here, have given occasion for much alarm... We therefore, the only Magistrates resident in the Borough, take the liberty of requesting that you will give orders for three Troops of some Horse Regiment to march immediately to this Place, and be assisting us in the quelling any Riots which may arise in Leicester. If it should be inconvenient... we request you will have the goodness to order as many as you can". | N27: 23 Jul 1791 | O27: 1791-07-23 | P27: =IF(O27="","",VALUE(LEFT(O27,4))) -> 1791 | Q27: Leicester | R27: Leicester | S27: Leicestershire | T27: Jno Darnes (Mayor), Henry Watchorn, W. Clark - magistrates | U27: Mayor / corporation | V27: Secretary at War (copy sent to Home Office) | W27: =IF(O27="","",INDEX(Lookups!$B$2:$B$27,MATCH(O27,Lookups!$A$2:$A$27,1))) -> Dundas | X27: Radical / political | Y27: Pre-emptive | Z27: Unclear | AA27: Three troops of horse | AB27: N | AI27: ROUTE: request addressed to the Secretary at War, not the Home Secretary; copy filed in HO 42. Docket 22 Jul (letter dated 23 Jul - CHECK). Mayor's name read as 'Darnes' - CHECK.
A28: HO42-0027 | B28: E22 | C28: Request for troops | D28: Y | E28: HO 42/19 | F28: HO-42-19_04.pdf | G28: 9-10, 16, 48-54 | H28: ff.256-257, 262, 294-300 | I28: Folio stamp | K28: Digitised (TNA PDF) | L28: Key quote only | M28: "considerable Bodies of disorderly people in this Neighbourhood have lately several times assembled... with the Riotous Intention of preventing the Commissioners acting under the Authority of an Inclosure Bill... burnt the farming property and broke the Windows of several Houses... openly avowed their Intentions of laying open the Inclosures... it is earnestly requested that you Sir will have the Goodness of affording immediate Military Assistance to suppress the first attempts to rioting... and to prevent their Connection with the Rioters from Birmingham". | N28: 23 Jul 1791 | O28: 1791-07-23 | P28: =IF(O28="","",VALUE(LEFT(O28,4))) -> 1791 | Q28: Sheffield | R28: Sheffield | S28: Yorkshire (W. Riding) | T28: Jas Wilkinson JP; Thos Eyre, Collector for the Town; Joseph Ward, Master Cutler | U28: Magistrate / JP | V28: Henry Dundas | W28: =IF(O28="","",INDEX(Lookups!$B$2:$B$28,MATCH(O28,Lookups!$A$2:$A$28,1))) -> Dundas | X28: Enclosure | Y28: Actual | Z28: Unclear | AA28: "speedy and effective Military Assistance" | AB28: N | AC28: Whitehall 25 Jul (f.262, Dundas absent): two troops of 4th Dragoons from York and two troops [light horse] from Nottingham ordered to Sheffield. Troops arrived 27-28 Jul; riot that night (gaol broken, Wilkinson's house at Broom Hall attacked, hay ricks burnt) dispersed by the military (ff.294-300). | AD28: Approved | AE28: 1791-07-25 | AF28: Whitehall | AG28: Home Office (Dundas absent) | AH28: Other | AI28: ANTI-ENCLOSURE riots + fear of Birmingham spillover (disturbance type: enclosure - consider adding 'Enclosure' to vocabulary). Signers met privately to avoid a public meeting that 'might excite public suspicions'. Request route: direct. Rioters attacked the requesting magistrate's house after troops arrived.
A29: HO42-0028 | B29: E22 | C29: Request for troops | D29: Y | E29: HO 42/19 | F29: HO-42-19_05.pdf | G29: 47 | H29: f.354 | I29: Folio stamp | K29: Digitised (TNA PDF) | L29: Key quote only | M29: "every thing has remain'd in a state of perfect Tranquillity, but this can only be attributed to the Appearance of the Military... for the Number of treasonable Inscriptions on Walls and Doors and frequent nocturnal Exclamations in the Streets such as 'No King' 'No Corn Bill' 'No Taxes' &c and the incendiary Letters... give just Grounds of fear that, if the Military were remov'd before all the Causes which gave Rise to the Commotions had subsided the worst of Consequences would in all probability immediately ensue & therefore I must beg Leave once more to express the Wish of the Town in general that they may be permitted to remain here". | N29: 31 Jul 1791 | O29: 1791-07-31 | P29: =IF(O29="","",VALUE(LEFT(O29,4))) -> 1791 | Q29: Sheffield | R29: Sheffield | S29: Yorkshire (W. Riding) | T29: Thos Eyre, Town Collector | U29: Other official | V29: Henry Dundas | W29: =IF(O29="","",INDEX(Lookups!$B$2:$B$29,MATCH(O29,Lookups!$A$2:$A$29,1))) -> Dundas | X29: Radical / political | Y29: Pre-emptive | Z29: N | AA29: Retain troops already sent | AB29: Y | AI29: REQUEST TO KEEP TROOPS (same question as Birmingham May 1794 - pending JV's answer). Same episode as HO42-0027. Also 1 Aug (ff.367-368): West Riding magistrates at Sheffield ask Govt to fund prosecutions of rioters; riot began by breaking the debtors' prison, neighbourhood riots 'in avowed & actual Opposition to an Act... for an Inclosure of waste Ground'.
A30: HO42-0029 | B30: E23 | C30: Corps founded | D30: Y | E30: HO 42/19 | F30: HO-42-19_08.pdf | G30: 48-50 | H30: ff.570-572 | I30: Folio stamp | K30: Digitised (TNA PDF) | L30: Key quote only | M30: Covering letter: gentlemen have signed "the Inclosed Association calculated for their mutual Protection against any sudden Rising of the Lower Class of People". Resolution (f.571): "We who subscribe our Names, reflecting upon the late violent insurrections arising from no publick provocation or principle whatever, but from a desire of Equality and Plunder... engage upon the first appearance or symptoms of such Evils to assemble not only all the Chief Constables and Petty constables but also our several Tenants and Servants, to Arm them and to resort to the Parts where the Evil exists... We conceive that if the Lord Lieutenant should judge proper to obtain a discretional power from Government to call for Military Aid without loss of time... such timely exertions would be more than superior to the Mob in its first stage". | N30: 6 Sept 1791 | O30: 1791-09-06 | P30: =IF(O30="","",VALUE(LEFT(O30,4))) -> 1791 | Q30: Snitterfield | R30: Snitterfield | S30: Warwickshire | T30: Unidentified correspondent for subscribing gentlemen (list of subscribers f.572) | U30: Loyalist association | V30: Home Office (inferred) | W30: =IF(O30="","",INDEX(Lookups!$B$2:$B$30,MATCH(O30,Lookups!$A$2:$A$30,1))) -> Dundas | X30: Preventive / general | AI30: Armed association of landowners, tenants and servants after the Priestley riots; also asks that the Lord Lieutenant get discretionary power to call military aid. CHECK: writer's name and place reading ('Snitterfield').
A31: HO42-0030 | B31: E24 | C31: Corps founded | D31: N | E31: HO 42/19 | F31: HO-42-19_08.pdf | G31: 52-53 | H31: ff.574-575 | I31: Folio stamp | K31: Digitised (TNA PDF) | L31: Key quote only | M31: "Lord Orford... has transmitted to you, an Association I had suggested to my Neighbours & afterwards to many of the principal Gentlemen of Landed property in this part of the County, at a period when the explosions of political Enthusiasm or Craft might break forth here or elsewhere, as at Birmingham. In this County in particular Vigilance was necessary, as upon any sudden decline of the Norwich Manufactures or upon a rise of provisions, Riots have followed & our Magistrates in this part of the County have sometimes been intimidated to inaction, or a disgraceful compromise." | N31: 7 Sept 1791 | O31: 1791-09-07 | P31: =IF(O31="","",VALUE(LEFT(O31,4))) -> 1791 | Q31: Rainham | R31: Raynham | S31: Norfolk | T31: [Lord] Townshend | U31: MP / peer | V31: Henry Dundas (via Lord Orford) | W31: =IF(O31="","",INDEX(Lookups!$B$2:$B$31,MATCH(O31,Lookups!$A$2:$A$31,1))) -> Dundas | X31: Preventive / general | AC31: Dundas to Earl of Orford, Whitehall Sept 1791 (HO 42/19_09 ff.632-634): motives deserve "the highest commendation, but I cannot help expressing some doubts whether the measure of putting People of the description mentioned by your Lordship in arms may not on general principles be liable to some objections... dangerous precedents generally originate in commendable motives". On discretionary power to call military aid: "the Military stationed in the County are ordered to obey at all times the Civil Magistrates in case of emergency". | AD31: Denied | AE31: 1791-09 | AF31: Whitehall | AG31: Henry Dundas | AH31: Other | AI31: Landowners' association in west Norfolk; association text itself (sent via Lord Orford) not seen here. Note magistrates 'intimidated to inaction, or a disgraceful compromise' in food riots. CHECK signer (Townshend). | Outcome coded Denied = arming discouraged (not formally refused); discretionary military power declined as unnecessary.
A32: HO42-0031 | B32: E25 | C32: Request for troops | D32: N | E32: HO 42/20 | F32: HO-42-20_3.pdf | G32: 33 | H32: f.177 | I32: Folio stamp | K32: Digitised (TNA PDF) | L32: Key quote only | M32: "the Journeymen Carpenters of this Town (who are a very powerful body of Men) had a meeting... & were heard to say, that if the abolition of the Slave Trade takes place, some Houses in the Town (which they had mark'd) shou'd be pull'd down... tho' I do not (I confess) apprehend much danger myself (having the 30th Regt of Foot here) yet... I shou'd recommend three Troops of Horse to be quarter'd in the neighbourhood till the ferment subsides a little viz.t One at Wigan, another at Warrington". | N32: 14 Apr 1792 | O32: 1792-04-14 | P32: =IF(O32="","",VALUE(LEFT(O32,4))) -> 1792 | Q32: Liverpool | R32: Liverpool | S32: Lancashire | T32: Henry Blundell, Mayor of Liverpool | U32: Mayor / corporation | V32: Henry Dundas | W32: =IF(O32="","",INDEX(Lookups!$B$2:$B$32,MATCH(O32,Lookups!$A$2:$A$32,1))) -> Dundas | X32: Labour / industrial | Y32: Pre-emptive | Z32: N | AA32: Three troops of horse (Wigan, Warrington, ...) | AB32: Y | AI32: Threat tied to slave-trade abolition (carpenters/shipwrights dependent on the trade). Second page not read - CHECK third location.
A33: HO42-0032 | B33: E26 | C33: Request for troops | D33: N | E33: HO 42/20 | F33: HO-42-20_3.pdf | G33: 35-38 | H33: ff.179-182 | I33: Folio stamp | K33: Digitised (TNA PDF) | L33: Key quote only | M33: "the great body of Carpenters intended to leave their work on Monday Morning unless their Wages were advanced... perhaps you will be so good, Sir, as to order One of the Troops of Grays, which are now at Manchester into Warrington or at least send Orders to the Commanding Officer in Manchester to march a Troop or two, if Circumstances shou'd compel me to call for them... There seems too general an appearance of discontent amongst all Artificers & Labourers". Encloses flatmen's notice (coal flats) demanding 1s per ton per trip. | N33: 27 May 1792 | O33: 1792-05-27 | P33: =IF(O33="","",VALUE(LEFT(O33,4))) -> 1792 | Q33: Liverpool | R33: Liverpool | S33: Lancashire | T33: Henry Blundell, Mayor of Liverpool | U33: Mayor / corporation | V33: Henry Dundas | W33: =IF(O33="","",INDEX(Lookups!$B$2:$B$33,MATCH(O33,Lookups!$A$2:$A$33,1))) -> Dundas | X33: Labour / industrial | Y33: Contingent | Z33: N | AA33: One troop of Greys to Warrington, or standing orders to march 1-2 troops on call | AB33: Y | AC33: Dundas 30 May (acknowledged 5 Jun, f.181: 'very much obliged by your attention to my request'). 5 Jun: no disturbance, merchants conceded part of carpenters' demand. "I should have been able to have suppressed any Riot, but I judg'd it prudent to be guarded against the worst & my reason for requesting Horse was, I think for dispersing a Mob, One Troop of Horse is better than half a Regt of Foot for avoiding blood shed". | AD33: Approved | AE33: 1792-05-30 | AH33: Other | AI33: Wage strike (carpenters, coal flatmen). Key rationale: cavalry preferred to infantry to avoid bloodshed. Mayor also urges Govt to build Anglican churches in new manufacturing villages (Methodists 'inimical to our happy Constitution').
A34: HO42-0033 | B34: E27 | C34: Request for troops | D34: N | E34: HO 42/20 | F34: HO-42-20_3.pdf | G34: 39-40 | H34: ff.183-184 | I34: Folio stamp | K34: Digitised (TNA PDF) | L34: Key quote only | M34: "the appearance of Assistance from the Military has had the very best Effect, the Mob are dispers'd & the people began to return yester' Morning to their Work... We are under very particular obligations to Major Ramsay of the Grays for the immediate Assistance he afforded us; he only rec'd our Express on Wednesday Morning at 5 o'Clock & he had two Troops in Wigan before One... This Riot by being taken in time (& which wou'd certainly have spread very far) has in my Opinion sav'd many from the Gallows". | N34: 7 Oct 1792 | O34: 1792-10-03 | P34: =IF(O34="","",VALUE(LEFT(O34,4))) -> 1792 | Q34: Wigan collieries (letter from Liverpool) | R34: Wigan | S34: Lancashire | T34: Henry Blundell, Mayor of Liverpool (as coal proprietor) | U34: Mayor / corporation | V34: Henry Dundas | W34: =IF(O34="","",INDEX(Lookups!$B$2:$B$34,MATCH(O34,Lookups!$A$2:$A$34,1))) -> Dundas | X34: Labour / industrial | Y34: Actual | Z34: Unclear | AA34: Express to Major Ramsay (Greys) - two troops; infantry under Capt Hall | AB34: Y | AC34: Two troops of Greys at Wigan within 8 hours of express; HO letter of 3 Oct acknowledged. | AD34: Approved | AE34: 1792-10-03 | AH34: Other | AI34: ROUTE: express sent DIRECTLY to the military commander (Major Ramsay), HO informed - 'local request, reported' route. Colliers' riot, engines stopped 2 days. Date (ISO) is approx. date of request (Wednesday before 7 Oct = 3 Oct) - CHECK. Cavalry released, infantry kept at Wigan.
A35: HO42-0034 | B35: E28 | C35: Request for troops | D35: N | E35: HO 42/20 | F35: HO-42-20_4.pdf | G35: 16-17 | H35: ff.243-244 | I35: Folio stamp | K35: Digitised (TNA PDF) | L35: Key quote only | M35: "a Disorder in the Town having happened the night before... occasioned by a Disagreement between some of the military and the populace... a more serious Affray took place between the military and the Inhabitants than any that had before happened... We have therefore requested the Commanding Officer of the Regiment at Nottingham... to make the Exchange but as there may be some Danger that whilst any of the same Regiment remain here that the Disputes... may not be forgotten We therefore submit it to you with great Deference whether it might not contribute to the Quiet of this place to send here immediately a part of some other Corps." | N35: 10-11 May 1792 | O35: 1792-05-10 | P35: =IF(O35="","",VALUE(LEFT(O35,4))) -> 1792 | Q35: Sheffield | R35: Sheffield | S35: Yorkshire (W. Riding) | T35: Saml Tooker, Fr. Edmunds, B. Frank (West Riding JPs) | U35: Magistrate / JP | V35: Henry Dundas (inferred) | W35: =IF(O35="","",INDEX(Lookups!$B$2:$B$35,MATCH(O35,Lookups!$A$2:$A$35,1))) -> Dundas | X35: Other / unclear | Y35: Actual | Z35: N | AA35: Replace quartered troops with part of another corps | AB35: Y | AI35: Riot between soldiers and townspeople (troops stationed since July 1791 enclosure riots). Request to SWAP troops, not add - borderline. Also asked CO at Nottingham directly (local route).
A36: HO42-0035 | B36: E29 | C36: Request for troops | D36: N | E36: HO 42/20 | F36: HO-42-20_4.pdf | G36: 64 | H36: f.289 | I36: Folio stamp | K36: Digitised (TNA PDF) | L36: Key quote only | M36: "We are honor'd with your favor of 23d. signifying approbation of our Calling in the Military from Kidderminster and Bromsgrove, and are happy to inform you the Town is at present in a State of perfect tranquility... the next week being Holiday presume it may be prudent to continue the present Troops." | N36: 25 May 1792 | O36: 1792-05-25 | P36: =IF(O36="","",VALUE(LEFT(O36,4))) -> 1792 | Q36: Birmingham | R36: Birmingham | S36: Warwickshire | T36: J. Carles & R. Spencer (magistrates) | U36: Magistrate / JP | V36: Henry Dundas | W36: =IF(O36="","",INDEX(Lookups!$B$2:$B$36,MATCH(O36,Lookups!$A$2:$A$36,1))) -> Dundas | X36: Other / unclear | Y36: Report only | Z36: Unclear | AA36: Troops from Kidderminster & Bromsgrove (already called); keep them over holiday week | AB36: Y | AC36: HO letter of 23 May approved their calling in the military. | AD36: Approved | AE36: 1792-05-23 | AH36: Other | AI36: ROUTE: local request to nearby garrisons, then reported; plus request to KEEP troops. Cause of May 1792 Birmingham disturbance not stated here - CHECK neighbouring folios.
A37: HO42-0036 | B37: E30 | C37: Request for troops | D37: Y | E37: HO 42/20 | F37: HO-42-20_4.pdf | G37: 76-77 | H37: ff.301-302 | I37: Folio stamp | K37: Digitised (TNA PDF) | L37: Key quote only | M37: "The Magistrates of this Borough being under some apprehensions of a Riot, a request was made to the Secretary at War in the Month of August last, that the Commanding Officer at York might have directions to Order a sufficient number of Troops to march to Leeds immediately upon a requisition... signed by the Mayor or Recorder and two Aldermen... we therefore request that such directions may be given... it is not our intention to call for Military aid till we think it safe no longer to be without it". | N37: 26 May 1792 | O37: 1792-05-26 | P37: =IF(O37="","",VALUE(LEFT(O37,4))) -> 1792 | Q37: Leeds | R37: Leeds | S37: Yorkshire (W. Riding) | T37: Wade Browne, Mayor | U37: Mayor / corporation | V37: Henry Dundas | W37: =IF(O37="","",INDEX(Lookups!$B$2:$B$37,MATCH(O37,Lookups!$A$2:$A$37,1))) -> Dundas | X37: Preventive / general | Y37: Contingent | Z37: N | AA37: Standing orders to CO at York to march sufficient troops on the Mayor's requisition | AB37: N | AI37: Earlier request Aug 1791 to Secretary at War (granted: 4th Dragoons at Pontefract) - a second, unlogged request; orders leaked and were 'publickly talked of at Leeds'. Asks CO not to divulge instructions. Follows the royal proclamation of 21 May 1792 against seditious writings.
A38: HO42-0037 | B38: E31 | C38: Request for troops | D38: N | E38: HO 42/20 | F38: HO-42-20_5.pdf | G38: 44, 48, 60, 62-67 | H38: ff.352, 357, 369, 371-376 | I38: Folio stamp | K38: Digitised (TNA PDF) | L38: Key quote only | M38: 6 Jun: "there are considerable Numbers of People in the Streets which make it advisable to continue the Military for a short Time, after which they propose to dismiss a part of them and to keep a small Number to patrole the Streets till tomorrow Morning, as was done on Tuesday Night". 8 Jun: "It was thought necessary from the Appearance & Behaviour of the People about 8 o'Clock to order a small party of the Horse Guards to patrole the Street for some time but they are now dismissed". | N38: 6-10 Jun 1792 | O38: 1792-06-05 | P38: =IF(O38="","",VALUE(LEFT(O38,4))) -> 1792 | Q38: Mount Street & South Audley Street, Westminster | R38: London (Mayfair) | S38: Middlesex | T38: Magistrates acting in Mount Street (Baker, Keene, Bond) | U38: Magistrate / JP | V38: Evan Nepean (Under-Secretary) | W38: =IF(O38="","",INDEX(Lookups!$B$2:$B$38,MATCH(O38,Lookups!$A$2:$A$38,1))) -> Dundas | X38: Other / unclear | Y38: Report only | Z38: Unclear | AA38: Military / small party of Horse Guards to patrol | AB38: Y | AI38: ROUTE: troops called locally by magistrates, reported to HO by half-hourly notes. Cause of Mount Street riots not stated in these notes - CHECK. St George's Hanover Square vestry thanks Horse Guards officers and Maj-Gen Buckley 11 Jun (ff.371-376). 10 Jun: crowd dispersed 'without the Appearance of any Soldier or even of any Constable'.
A39: HO42-0038 | B39: E32 | C39: Barracks | D39: N | E39: HO 42/20 | F39: HO-42-20_7.pdf | G39: 53 | H39: f.528 | I39: Folio stamp | K39: Digitised (TNA PDF) | L39: Key quote only | M39: "Not being able to get a place in the Town or even in the Vicinity of Sheffield for the temporary accommodation of the Troops, He has entered into engagements for building Barracks at the distance of about three quarters of a Mile from the Town, on the Halifax Road - The distance will prevent too free an intercourse between the Soldiery and Inhabitants, without occasioning any inconvenience in obtaining supplies from the market... The buildings will be so constructed that they may at any time, if necessary, be enlarged." | N39: 19 Jul 1792 | O39: 1792-07-19 | P39: =IF(O39="","",VALUE(LEFT(O39,4))) -> 1792 | Q39: Sheffield | R39: Sheffield | S39: Yorkshire (W. Riding) | T39: Col. Oliver De Lancey (Barrack-Master), to the Secretary at War; abstract read by the King | U39: Military officer | V39: Secretary at War (abstract filed in HO 42) | W39: =IF(O39="","",INDEX(Lookups!$B$2:$B$39,MATCH(O39,Lookups!$A$2:$A$39,1))) -> Dundas | X39: Preventive / general | AA39: Barracks for 3 troops of dragoons | AI39: Part of the 1792 barrack-building programme for manufacturing towns (cover: 'Plans &c of Barracks to be built at Sheffield, Manchester & Nottingham under agreements made by Col. de Lancey', July 1792, 'Read by The King'). Cost estimate (f.515): Sheffield 3 troops £2000; Manchester 6 troops £7900; Nottingham 3 troops £3800; Birmingham 3 troops £5000. KEY: siting chosen to limit contact between soldiers and inhabitants - links to May 1792 soldier-townspeople riot (HO42-0034). Land from Vincent Eyre.
A40: HO42-0039 | B40: E33 | C40: Barracks | D40: N | E40: HO 42/20 | F40: HO-42-20_7.pdf | G40: 61 | H40: f.532 | I40: Folio stamp | K40: Digitised (TNA PDF) | L40: Key quote only | M40: "The speculations of the Inhabitants have greatly increased the price of Land in and about Manchester - He has obtained Six acres at three half pence per Yard, amounting to an Annual rent of £187.14 from Mr Egerton half a mile to the Southward of the Town. The extent is absolutely necessary for the purposes of discipline." | N40: 7 Aug 1792 | O40: 1792-08-07 | P40: =IF(O40="","",VALUE(LEFT(O40,4))) -> 1792 | Q40: Manchester | R40: Manchester | S40: Lancashire | T40: Col. Oliver De Lancey (Barrack-Master), to the Secretary at War; abstract read by the King | U40: Military officer | V40: Secretary at War (abstract filed in HO 42) | W40: =IF(O40="","",INDEX(Lookups!$B$2:$B$40,MATCH(O40,Lookups!$A$2:$A$40,1))) -> Dundas | X40: Preventive / general | AA40: Barracks for 6 troops of dragoons | AI40: Part of the 1792 barrack-building programme for manufacturing towns (cover: 'Plans &c of Barracks to be built at Sheffield, Manchester & Nottingham under agreements made by Col. de Lancey', July 1792, 'Read by The King'). Cost estimate (f.515): Sheffield 3 troops £2000; Manchester 6 troops £7900; Nottingham 3 troops £3800; Birmingham 3 troops £5000. Builder Chas. McNevin. Context in same file: May 1792 'spirit of combination' among 2nd Dragoons at Manchester over provision prices (ff.520-523).
A41: HO42-0040 | B41: E34 | C41: Barracks | D41: N | E41: HO 42/20 | F41: HO-42-20_7.pdf | G41: 68 | H41: f.536 | I41: Folio stamp | K41: Digitised (TNA PDF) | L41: Key quote only | M41: "he has taken 3 Acres of Land within half a mile of Nottingham on the Derby Road upon a building lease, from the Duke of Newcastle for the term of 61 Years at the rent of £60 per Ann." | N41: 17 Aug 1792 | O41: 1792-08-17 | P41: =IF(O41="","",VALUE(LEFT(O41,4))) -> 1792 | Q41: Nottingham | R41: Nottingham | S41: Nottinghamshire | T41: Col. Oliver De Lancey (Barrack-Master), to the Secretary at War; abstract read by the King | U41: Military officer | V41: Secretary at War (abstract filed in HO 42) | W41: =IF(O41="","",INDEX(Lookups!$B$2:$B$41,MATCH(O41,Lookups!$A$2:$A$41,1))) -> Dundas | X41: Preventive / general | AA41: Barracks for 3 troops of dragoons | AI41: Part of the 1792 barrack-building programme for manufacturing towns (cover: 'Plans &c of Barracks to be built at Sheffield, Manchester & Nottingham under agreements made by Col. de Lancey', July 1792, 'Read by The King'). Cost estimate (f.515): Sheffield 3 troops £2000; Manchester 6 troops £7900; Nottingham 3 troops £3800; Birmingham 3 troops £5000. Builders Samuel & William Stretton.
A42: HO42-0041 | B42: E35 | C42: Barracks | D42: N | E42: HO 42/20 | F42: HO-42-20_7.pdf | G42: 46 | H42: f.524 | I42: Folio stamp | K42: Digitised (TNA PDF) | L42: Key quote only | M42: "Not being able to get a place for the purpose of a temporary Barrack; he has entered into engagements for Building, and has taken four acres of Land at the West end of the Town from Mr John Brook... Four acres of Land situated at Ashsted near Birmingham to be leased for Eighty three years at the Rent of £80 per Ann." | N42: 24 Aug 1792 | O42: 1792-08-24 | P42: =IF(O42="","",VALUE(LEFT(O42,4))) -> 1792 | Q42: Birmingham | R42: Birmingham | S42: Warwickshire | T42: Col. Oliver De Lancey (Barrack-Master), to the Secretary at War; abstract read by the King | U42: Military officer | V42: Secretary at War (abstract filed in HO 42) | W42: =IF(O42="","",INDEX(Lookups!$B$2:$B$42,MATCH(O42,Lookups!$A$2:$A$42,1))) -> Dundas | X42: Preventive / general | AA42: Barracks for 3 troops of dragoons | AI42: Part of the 1792 barrack-building programme for manufacturing towns (cover: 'Plans &c of Barracks to be built at Sheffield, Manchester & Nottingham under agreements made by Col. de Lancey', July 1792, 'Read by The King'). Cost estimate (f.515): Sheffield 3 troops £2000; Manchester 6 troops £7900; Nottingham 3 troops £3800; Birmingham 3 troops £5000. Ashted. Lessor John Brook (the Under-Sheriff who requested troops in July 1791, HO42-0021 - CHECK same person).
A43: HO42-0042 | B43: E36 | C43: Barracks | D43: N | E43: HO 42/21 | F43: HO-42-21_01.pdf; HO-42-21_06.pdf | G43: 109 | H43: [unstamped, between ff.72-74] | I43: Unclear - check | K43: Digitised (TNA PDF) | L43: Key quote only | M43: "A Plan of the Bull Premises Coventry. Survey'd Sept. 5th 1792 by W. Baylis." [2 acres 3 roods 5 perches, High Street / Warwick Road; signed by Col. DeLancey] | Covering letter (HO 42/21_06 f.491), DeLancey to Sir George Yonge (Secretary at War), Coventry 11 Sep 1792: "having in the course of my enquiries for a place that I could have fitted up as a temporary Barrack for three Troops of Dragoons been informed that the Lease of the Bull Inn, a large old Building, was just expired... the difficulties with respect to Land were great, most of that about the Town being subject to priviledges enjoyed by the Inhabitants". Instructions to Major Belford (f.496, 7 Sep): ordered by the Secretary at War "to procure or Erect a Barrack at this place, for three Troops of Dragoons"; Bull Inn purchased from James Gunman. Plans ff.497-499. | N43: 5 Sept 1792 | O43: 1792-09-05 | P43: =IF(O43="","",VALUE(LEFT(O43,4))) -> 1792 | Q43: Coventry | R43: Coventry | S43: Warwickshire | T43: Col. Oliver DeLancey to Sir George Yonge, Secretary at War | U43: Military officer | V43: Unclear (filed in HO 42) | W43: =IF(O43="","",INDEX(Lookups!$B$2:$B$43,MATCH(O43,Lookups!$A$2:$A$43,1))) -> Dundas | X43: Preventive / general | AA43: Barracks for 3 troops of dragoons (Bull Inn converted) | AI43: Site plan for barracks at Coventry (Bull Inn premises) - part of 1792 programme (cf. HO42-0038 to 0041). Coventry had requested a regiment in July 1791 (HO42-0023). Covering letter found in 21_06.
A44: HO42-0043 | B44: E37 | C44: Request for troops | D44: N | E44: HO 42/21 | F44: HO-42-21_04.pdf | G44: 62 | H44: f.323 | I44: Folio stamp | K44: Digitised (TNA PDF) | L44: Key quote only | M44: Copy, Capt J.G. Le Marchant (Queen's Dragoon Guards), Bradford [on Avon], 15 Aug 1792: "Late last Night, Troops were required of me by the Sheriff of Somerset to be stationed at Cammerton, the Inhabitants being greatly alarmed from the assembling of a considerable Body of Colliers. I in consequence detached a Party, and since which have received their report, saying the Colliers continue assembled, but are not riotous." | N44: 14-15 Aug 1792 | O44: 1792-08-14 | P44: =IF(O44="","",VALUE(LEFT(O44,4))) -> 1792 | Q44: Camerton | R44: Camerton | S44: Somerset | T44: Sheriff of Somerset (request); reported by Capt J.G. Le Marchant | U44: Other official | V44: Local commander (Capt Le Marchant, Bradford-on-Avon) | W44: =IF(O44="","",INDEX(Lookups!$B$2:$B$44,MATCH(O44,Lookups!$A$2:$A$44,1))) -> Dundas | X44: Labour / industrial | Y44: Pre-emptive | Z44: Unclear | AA44: Troops stationed at Camerton; a party of Queen's Dragoon Guards sent | AB44: Y | AC44: Party detached immediately by the local commander. | AD44: Approved | AH44: Other | AI44: ROUTE: local request (Sheriff -> nearest officer), copy forwarded to HO. Part of Aug 1792 Kingswood/Somerset colliers' wage strike - see Bristol report f.307.
A45: HO42-0044 | B45: E37 | C45: Other | D45: N | E45: HO 42/21 | F45: HO-42-21_04.pdf | G45: 35-37 | H45: ff.307-309 | I45: Folio stamp | K45: Digitised (TNA PDF) | L45: Key quote only | M45: "a large body of Colliers who work the Mines in the Neighbourhood of this City encouraged as is supposed by the success of the Shoemakers and other tradesmen who in this place lately stood out for an increase of Wages, assembled and in a peremptory manner demanded... an addition of two Shillings per Week... They have hitherto met with no opposition from the Magistrates of the County of Gloucester nor has the corporation of this City apparently taken any measures to counteract this alarming combination". About 2000 Gloucestershire colliers passed through Bristol to compel Somerset miners (Bedminster, Ashton, Nailsea) to join. | N45: 9 Aug 1792 | O45: 1792-08-09 | P45: =IF(O45="","",VALUE(LEFT(O45,4))) -> 1792 | Q45: Bristol / Kingswood | R45: Bristol | S45: Gloucestershire / Bristol | T45: George Monro | U45: Private individual | V45: Home Office (Under-Secretary, inferred) | W45: =IF(O45="","",INDEX(Lookups!$B$2:$B$45,MATCH(O45,Lookups!$A$2:$A$45,1))) -> Dundas | X45: Labour / industrial | Y45: Report only | Z45: Y | AI45: Report of strike/combination, no request; magistrates inactive. Context for E37 Camerton request.
A46: HO42-0045 | B46: E27 | C46: Request for troops | D46: Y | E46: HO 42/22 | F46: HO-42-22_01.pdf | G46: 46-47, 98-99 | H46: ff.29-30, 58-59 | I46: Folio stamp | K46: Digitised (TNA PDF) | L46: Key quote only | M46: 1 Oct 1792: colliers near Wigan, "near 500", demand "an extravagant advance of Wages" and threaten "to destroy the Works, by pulling up the Engines, throwing down the Wheels & filling up the Pits... I apply'd to Major Campbell commanding the 30th Regt to march a Company or two of his Regt to assist Wigan to assist the Civil Power (which is by no means equal to quell the present disturbance) but he declines it without express orders from the Secretary of State. I am requested by the Coal Owners... to entreat of you to give orders to Major Campbell & the Commanding Officer at Manchester to march part of their Men to Wigan in aid of the Magistrates." 3 Oct: Campbell "at length... prevail'd upon to detach two Companies"; mob grown "from near 500 to 1000"; express to Manchester for a troop of horse; "it will be found absolutely necessary to have a Regiment of Horse & Two of Infantry always in this County". | N46: 1-3 Oct 1792 | O46: 1792-10-01 | P46: =IF(O46="","",VALUE(LEFT(O46,4))) -> 1792 | Q46: Wigan collieries (letters from Liverpool) | R46: Wigan | S46: Lancashire | T46: Henry Blundell, Mayor of Liverpool (for the coal owners) | U46: Mayor / corporation | V46: Henry Dundas | W46: =IF(O46="","",INDEX(Lookups!$B$2:$B$46,MATCH(O46,Lookups!$A$2:$A$46,1))) -> Dundas | X46: Labour / industrial | Y46: Actual | Z46: Y | AA46: Orders for 30th Regt (1-2 companies) and Manchester troops to march to Wigan; later a regiment of horse and two of infantry to be kept in the county | AB46: Y | AC46: Campbell detached two companies (Capt Hall) by canal boat 3 Oct; horse from Manchester reached Wigan 2pm 3 Oct. HO reply 3 Oct acknowledged (HO42-0033). Copy sent to War Office. | AD46: Approved | AE46: 1792-10-03 | AH46: Other | AI46: ORIGINAL REQUEST for the Wigan episode (HO42-0033 is the 7 Oct follow-up). KEY: local commander refused to act on the Mayor's application 'without express orders from the Secretary of State' - evidence that HO authorisation mattered even when a garrison was at hand. Mayor wrote as coal proprietor/for coal owners.
A47: HO42-0046 | B47: E38 | C47: Barracks | D47: N | E47: HO 42/22 | F47: HO-42-22_01.pdf | G47: 2-35 | H47: ff.3-24, 119 | I47: Folio stamp | K47: Digitised (TNA PDF) | L47: Key quote only | M47: "I arrived here on Saturday the 22 September, and having after very diligent enquiry been fully convinced that no place could be got for the purpose of a temporary Barrack for four Troops of Dragoons, I therefore, in compliance with your Orders under such circumstances, proceeded to build, and accordingly entered into a Treaty for the purchase of the remaining term of Eighteen years of a Lease of Eleven acres of Ground, situated in the Hamlet of Pockthorp, just without the Gates of the Town, held under the Dean and Chapter of Norwich". | N47: 1 Oct 1792 | O47: 1792-10-01 | P47: =IF(O47="","",VALUE(LEFT(O47,4))) -> 1792 | Q47: Norwich (Pockthorpe) | R47: Norwich | S47: Norfolk | T47: Col. Oliver DeLancey to Sir George Yonge, Secretary at War | U47: Military officer | V47: Secretary at War (filed in HO 42) | W47: =IF(O47="","",INDEX(Lookups!$B$2:$B$47,MATCH(O47,Lookups!$A$2:$A$47,1))) -> Dundas | X47: Preventive / general | AA47: Barracks for 4 troops of dragoons | AI47: 1792 barracks programme (cf. HO42-0038 to 0042). File includes articles of agreement, specification, elevation and ground plan (ff.13-24), and DeLancey instructions to the officer commanding at Norwich (f.119). Norwich had active radical societies in 1792 (HO 42/20_2).
A48: HO42-0047 | B48: E39 | C48: Barracks | D48: Y | E48: HO 42/22 | F48: HO-42-22_02.pdf | G48: 94, 108-109 | H48: ff.119, 156-157 | I48: Folio stamp | K48: Digitised (TNA PDF) | L48: Key quote only | M48: "In consequence of Orders communicated to Colonel De Lancey, on the 24th of June 1792, to go to Sheffield, and there put three Troops of Dragoons into temporary Barracks, by hiring Houses, Barns, or other places... after which to do the same for a Regiment of Dragoons at Manchester, for three Troops each at Nottingham, Birmingham and Coventry, and for four Troops at Norwich." ... "the expence of building the Barracks... has been carried much higher from their being placed in those Towns of the Kingdom where the Commerce and Manufactures are in the most flourishing State". Recapitulation: Sheffield rent £20, building £2000; Manchester £187.14 / £7900; Nottingham £60 / £3800; Birmingham £80 / £5000; Coventry land purchase £1500, building £2300; Norwich land £800, rent £6.3, building £6300; totals land £2300, rent £353.17, building c.£27,300. | N48: 12 Oct 1792 | O48: 1792-10-12 | P48: =IF(O48="","",VALUE(LEFT(O48,4))) -> 1792 | Q48: London (programme report: Sheffield, Manchester, Nottingham, Birmingham, Coventry, Norwich) | R48: [National programme] | S48: [Multiple] | T48: Col. Oliver DeLancey | U48: Military officer | V48: Government (report) | W48: =IF(O48="","",INDEX(Lookups!$B$2:$B$48,MATCH(O48,Lookups!$A$2:$A$48,1))) -> Dundas | X48: Preventive / general | AI48: SUMMARY DOCUMENT for the 1792 manufacturing-town barracks programme (rows HO42-0038 to 0042, 0046). Orders dated 24 Jun 1792 - i.e. shortly after the 21 May proclamation and the May 1792 Sheffield/Birmingham/Mount Street troubles. Original plan was TEMPORARY barracks in hired buildings; building forced by lack of premises. Figures read from faint recapitulation - CHECK Coventry and Norwich building figures.
A49: HO42-0048 | B49: E40 | C49: Request for troops | D49: Y | E49: HO 42/22 | F49: HO-42-22_03.pdf | G49: 7, 9 | H49: f.165 (148) | I49: Folio stamp | K49: Digitised (TNA PDF) | L49: Key quote only | M49: Extract, Mayor of Leicester to the Secretary at War, 15 Oct 1792: "We have no threats or immediate appearance of tumult at this moment, but from the mutinous disposition of the lower order of People, which seems to become worse here every day, & from the last riot having happened without any foundation, & quite suddenly & unexpectedly, myself & my brother Justices do not think the Town safe for a day without Military. Within these few days 'Liberty & Equality' with many expressions of similar Tendency have been found written on some doors in several of the Streets - From the unheard of dearness of Coals & the extraordinarily high Price of Provisions, there seems quite as much Prospect of Tumult as there ever was." | N49: 15 Oct 1792 | O49: 1792-10-15 | P49: =IF(O49="","",VALUE(LEFT(O49,4))) -> 1792 | Q49: Leicester | R49: Leicester | S49: Leicestershire | T49: Mayor of Leicester (with fellow Justices) | U49: Mayor / corporation | V49: Secretary at War (extract filed in HO 42) | W49: =IF(O49="","",INDEX(Lookups!$B$2:$B$49,MATCH(O49,Lookups!$A$2:$A$49,1))) -> Dundas | X49: Food / provisions | Y49: Pre-emptive | Z49: Y | AA49: Military to remain/be stationed in the town | AB49: Unclear | AI49: ROUTE: to Secretary at War; extract forwarded to HO. Mixes food/fuel prices and radical slogans ('Liberty & Equality'). Refers to an earlier recent riot in Leicester - CHECK. Same town as July 1791 request (HO42-0026) but different episode.
A50: HO42-0049 | B50: E41 | C50: Request for troops | D50: N | E50: HO 42/22 | F50: HO-42-22_03.pdf | G50: 79 | H50: f.209 (189) | I50: Folio stamp | K50: Digitised (TNA PDF) | L50: Key quote only | M50: Capt M. Agnew (11th Dragoons), Norwich, 30 Oct 1792: "upon a requisition from the Mayor & Magistrates yesterday by express from thence I immediately ordered a Reinforcement which would arrive there this morning being obliged to call in the out Parties, the Mayor & Civil Magistrates here not choosing to part with any from this Quarter. The Detachment at Yarmouth consists of two Officers, 1 Qr. Mr., 2 Serjts, 3 Corpls & 35 Dragoons." | N50: 29-30 Oct 1792 | O50: 1792-10-29 | P50: =IF(O50="","",VALUE(LEFT(O50,4))) -> 1792 | Q50: Great Yarmouth (letter from Norwich) | R50: Great Yarmouth | S50: Norfolk | T50: Mayor & Magistrates of Yarmouth (requisition); reported by Capt M. Agnew, 11th Dragoons | U50: Mayor / corporation | V50: Local commander (Capt Agnew, Norwich) | W50: =IF(O50="","",INDEX(Lookups!$B$2:$B$50,MATCH(O50,Lookups!$A$2:$A$50,1))) -> Dundas | X50: Labour / industrial | Y50: Actual | Z50: Unclear | AA50: Reinforcement of dragoons; detachment of 2 officers + 35 dragoons | AB50: Y | AC50: Reinforcement ordered immediately by local commander; HO/War Office route for a detachment to Yarmouth also received. | AD50: Approved | AH50: Other | AI50: ROUTE: local requisition by express to the garrison commander, reported. Norwich magistrates refused to release their own troops - competition between towns for scarce troops. | CAUSE (HO 42/22_04 ff.219-222, 278): sailors' wage disturbance 22 Oct, then market riot over price of corn and provisions; threatening letter 21 Oct to Mayor Edm. Lacon ("your head shall com from your sholders... we have now select for this purpose 300"). Mayor reported to Secretary at War 28 Oct; Dundas to Marquis Townshend 2 Nov (f.243): orders given "sufficient to enable him to support the authority of the civil Magistrate". Townshend (31 Oct, f.219) asks that magistrates in disturbed districts "may have authority to call out the military". Mixed labour/food.
A51: HO42-0050 | B51: E42 | C51: Request for troops | D51: N | E51: HO 42/22 | F51: HO-42-22_04.pdf | G51: 35-42, 63 | H51: ff.247-252, 274 | I51: Folio stamp | K51: Digitised (TNA PDF) | L51: Key quote only | M51: Copy, North Shields 3 Nov 1792, to William Pitt: "The situation of this unfortunate place begins to be so extreemly alarming... a large fleet (about 400 sail) had accumulated... the Seamen discovered a disposition to Riot, & assembled in great numbers in different parts of the Towns of N. & South Shields, and in boats upon the River Tyne, insisting that the masters of all Ships should pay four Guineas Wages for the Voyage". Response (Nepean to R. Burdon, Castle Eden, 5 Nov, f.274): "three Companies of the 57th Regt have been ordered to repair to that place from Tynemouth Barracks to be in readiness to assist the Civil Magistrate in restoring Tranquillity and good order. The Martin Sloop has also been ordered to proceed to the Tyne". | N51: 3 Nov 1792 | O51: 1792-11-03 | P51: =IF(O51="","",VALUE(LEFT(O51,4))) -> 1792 | Q51: North & South Shields, River Tyne | R51: North Shields | S51: Northumberland / Durham | T51: R. Burdon (Castle Eden) / Shields correspondents (copy to Pitt) | U51: Private individual | V51: William Pitt (copy); Home Office | W51: =IF(O51="","",INDEX(Lookups!$B$2:$B$51,MATCH(O51,Lookups!$A$2:$A$51,1))) -> Dundas | X51: Labour / industrial | Y51: Actual | Z51: Unclear | AA51: Military and naval support (implied) | AB51: Y | AC51: Three companies of 57th Regt from Tynemouth Barracks + Martin sloop ordered; Mayor of Newcastle and Mr Bulmer of Shields informed. | AD51: Approved | AE51: 1792-11-05 | AF51: Whitehall | AG51: Evan Nepean | AH51: Other | AI51: Seamen's wage strike (Tyne), Oct-Nov 1792. CHECK writer of the 3 Nov copy and whether an explicit request for troops is made (letter is long, ff.247-252, only first page read). Tynemouth Barracks already existed.
A52: HO42-0051 | B52: E42 | C52: Request for troops | D52: Y | E52: HO 42/22 | F52: HO-42-22_05.pdf | G52: 3, 36-37, 69, 71-72 | H52: ff.283, 312-313, 315-316, 320 | I52: Folio stamp | K52: Digitised (TNA PDF) | L52: Key quote only | M52: Mayor of Newcastle James Rudman to Nepean, 8 Nov 1792, after a General Meeting of the Magistrates of Durham, Northumberland and Newcastle: "The Meeting was unanimously of opinion that the naval and military Force now here, even with the addition of the Martin Sloop... will not be sufficient to protect the civil Magistrate and the immense property in Shipping now in Harbour, if measures of coercion be resorted to... I have with the approbation of the Meeting requested of the Commanding Officer of the Troops at York that he will forward a Detachment to South Shields... and I have to express the earnest desire of the Meeting that you will be pleased to direct a Frigate or another Sloop of War, with a number of Marines on Board... and also that three or four Companies of any Regiment of Foot... may be marched here. The Ship owners cannot be prevailed upon to afford the Magistrates any specific information... under the dread of the Vengeance of the Rioters... it absolutely necessary that the force to be used should be so considerable as to leave no Hope to Resistance". | N52: 8 Nov 1792 | O52: 1792-11-08 | P52: =IF(O52="","",VALUE(LEFT(O52,4))) -> 1792 | Q52: Newcastle upon Tyne / South Shields | R52: Newcastle upon Tyne | S52: Northumberland | T52: James Rudman, Mayor of Newcastle, for general meeting of magistrates of Durham, Northumberland and Newcastle | U52: Mayor / corporation | V52: Evan Nepean (Under-Secretary) | W52: =IF(O52="","",INDEX(Lookups!$B$2:$B$52,MATCH(O52,Lookups!$A$2:$A$52,1))) -> Dundas | X52: Labour / industrial | Y52: Actual | Z52: Y | AA52: Detachment from York; a frigate or sloop with marines; 3-4 companies of foot | AB52: Y | AC52: Nepean 10 Nov (ff.315-316): Lord Grenville (acting) had already sent Hind frigate and Drake sloop to join Racehorse and Martin; 2 troops of cavalry at York ordered to readiness on Major Thompson's requisition, rest of York force on further requisition; letter enclosed to C-in-C Scotland - "There is not at this moment any Infantry nearer to Newcastle than Edinburgh." Adj-Gen Fawcett to Lord Adam Gordon, Edinburgh, 10 Nov (f.320): comply with any requisition from Newcastle magistrates "by detaching as large a body of Troops... as you can spare". | AD52: Approved | AE52: 1792-11-10 | AF52: Whitehall | AG52: Evan Nepean (for Lord Grenville) | AH52: Other | AI52: KEY: meeting of three benches requests troops; magistrates also requested York commander directly; government notes no infantry nearer than Edinburgh - illustrates scarcity of troops in the north in 1792. Same episode E42 as North Shields (HO42-0050). Earlier 5 Nov HO letter to Mayor (f.283) responding to Bulmer's request for 'some military, as well as Naval Force'. | Outcome (HO 42/22_06 ff.362, 382): 13 Nov sailors submitted to magistrates' arbitration, "the Dragoons are stoped at Durham", Martin sloop in harbour; writer urges a frigate "constantly attached to this port". 14 Nov Mayor: sailors gave way a little. HO to DeLancey 13 Nov (f.366) queries magistrates' unwillingness to lessen force at Tynemouth Barracks. | Burdon, Castle Eden 25 Nov (HO 42/22_08 f.503): riot terminated, Shields quiet, "beginning to supplicate a removal of the Ships of war"; hopes the 2 troops of horse at Durham will be ordered back to York "because the Durham people will be much disposed to grumble, if they are saddled for their neighbours offences" - local reluctance to host troops. | Ship-owners' meeting, S. Shields 28 Nov (HO 42/22_09 f.562): Government steps "were not seconded by the Civil Power"; magistrates "(except Mr Burdon) seemed rather to encourage than check the Riotous proceedings of the Seamen". | Renewed Dec 1792 (HO 42/23_01 ff.54-55, Rudman to Dundas, Newcastle 2 Dec): sailors meeting daily in larger body; Capt Rothe says press warrants could not be executed "and indeed it is evident that it would be dangerous to attempt it with the Force he has"; fears seamen "instigated by the Enemies of our Tranquillity". Insufficient-force statement, no explicit request on these pages.
A53: HO42-0052 | B53: E43 | C53: Corps founded | D53: Y | E53: HO 42/22 | F53: HO-42-22_06.pdf | G53: 54-61 | H53: ff.401- | I53: Folio stamp | K53: Digitised (TNA PDF) | L53: Key quote only | M53: "ANTE-LEVELLING SOCIETY instituted For supporting the Civil Power in suppressing Tumults and For maintaining the Constitutional Government of this Country in King, Lords and Commons" | N53: 17 Nov 1792 | O53: 1792-11-17 | P53: =IF(O53="","",VALUE(LEFT(O53,4))) -> 1792 | Q53: Ipswich (inferred from HO draft reply to Chas. [?], Ipswich, 17 Nov) | R53: Ipswich | S53: Suffolk | T53: Charles Stisted (Ipswich), forwarding Society resolutions | U53: Loyalist association | V53: Home Office | W53: =IF(O53="","",INDEX(Lookups!$B$2:$B$53,MATCH(O53,Lookups!$A$2:$A$53,1))) -> Dundas | X53: Radical / political | AI53: Early loyalist association (pre-dates Reeves's Crown and Anchor association of 20 Nov 1792). Explicitly 'for supporting the Civil Power in suppressing Tumults'. CHECK place (Ipswich) and correspondent name on f.400 docket; rules on following folios not fully read. | Stisted to [Lord?], Ipswich 20 Nov 1792 (HO 42/22_07 f.454): conduct "during the Disturbances here" approved by the King; "if arm'd Boats could always be in readiness to assist at the kind of Riot we had here, nothing would so effectually check the Rioters"; six prisoners taken. Implies a (probably seamen's) riot at Ipswich, Nov 1792 - CHECK for original report.
A54: HO42-0053 | B54: E44 | C54: Request for troops | D54: N | E54: HO 42/23 | F54: HO-42-23_05.pdf | G54: 97-98 | H54: ff.370-371 | I54: Folio stamp | K54: Digitised (TNA PDF) | L54: Key quote only | M54: Copy, W. Molesworth, Pencarrow near Bodmin, 14 Dec 1792: "the Miners in the Western Part of this County are extremely uneasy on account of an Idea which prevails amongst them that 'Corn is exported abroad from this Neighbourhood Wade Bridge & Padstow River'... I have in conjunction with Sir Francis Basset bought the Corn now cellered at Wade Bridge & We have ordered it to be immediately shipped for Porthleah (the Centre of the mining Country) on our Accounts... In case of any Riot or Tumult I beg to know how I am to act." | N54: 14 Dec 1792 | O54: 1792-12-14 | P54: =IF(O54="","",VALUE(LEFT(O54,4))) -> 1792 | Q54: Pencarrow near Bodmin (re Wadebridge/Padstow & West Cornwall mining country) | R54: Wadebridge | S54: Cornwall | T54: W. Molesworth | U54: Magistrate / JP | V54: Home Office (copy filed) | W54: =IF(O54="","",INDEX(Lookups!$B$2:$B$54,MATCH(O54,Lookups!$A$2:$A$54,1))) -> Dundas | X54: Food / provisions | Y54: Contingent | Z54: Unclear | AA54: Asks for instructions in case of riot (no force named) | AB54: Unclear | AI54: BORDERLINE: request for guidance, not explicit troop request. Shows gentry buying corn to pre-empt miners' food riot. Writer role (JP) inferred - CHECK. | Original also at HO 42/23_06 f.387.
A55: HO42-0054 | B55: E45 | C55: Corps founded | D55: N | E55: HO 42/23 | F55: HO-42-23_08.pdf | G55: 66 | H55: f.537 | I55: Folio stamp | K55: Digitised (TNA PDF) | L55: Key quote only | M55: Dundas to Earl of Mount Edgcumbe, Whitehall 26 Dec 1792 (copy): "I have had the honour of receiving your Lordships two letters of the 21 & 25 inst. on the subject of a proposal made by Mr Grenfell to raise a Body of Troops for the defence of the Coasts of Cornwall & Devon. If circumstances should hereafter occur which may lead to measures of that sort, I shall not fail to submit Mr Grenfell's proposal to the consideration of His Majesty's Ministers, provided he furnishes me in the mean time with a regular detail of the proposed Corps". | N55: 21-26 Dec 1792 | O55: 1792-12-21 | P55: =IF(O55="","",VALUE(LEFT(O55,4))) -> 1792 | Q55: Cornwall & Devon | R55: [Cornwall/Devon coast] | S55: Cornwall | T55: Mr Grenfell, via Earl of Mount Edgcumbe (Lord Lieutenant of Cornwall) | U55: Private individual | V55: Henry Dundas | W55: =IF(O55="","",INDEX(Lookups!$B$2:$B$55,MATCH(O55,Lookups!$A$2:$A$55,1))) -> Dundas | X55: Preventive / general | AC55: Deferred: to be submitted to Ministers if circumstances require, pending detailed plan. | AD55: Unknown | AE55: 1792-12-26 | AF55: Whitehall | AG55: Henry Dundas | AH55: Other | AI55: EXTERNAL DEFENCE (coast), not internal order - include for completeness; low relevance unless corps later used against riots. Grenfell likely Pascoe Grenfell (Cornish mining/merchant) - CHECK. Same file p.69 (f.539): a Highland corps proposal (Scotland, out of scope).
A56: HO42-0055 | B56: E46 | C56: Request for troops | D56: N | E56: HO 42/23 | F56: HO-42-23_11.pdf | G56: 31, 37-38 | H56: ff.737, 743-744 | I56: Folio stamp | K56: Digitised (TNA PDF) | L56: Key quote only | M56: St Austell, 20 Jan 1793 (to Lord Lieutenant): "I wrote you under much Alarm from the Conduct of the Tinners at our Market... they did wrong in attempting to regulate the Market Yesterday... it was certainly time to stop the Exportation of Corn, or the Farmers would not have kept enough in the County to keep the Inhabitants from Starving; tho I trust we shall have no further Bustle, yet I still think it will be prudent to have some Military at Hand, in Case these Men should persist in wanting to regulate the Price of every Thing in the Markets". | N56: 20 Jan 1793 | O56: 1793-01-20 | P56: =IF(O56="","",VALUE(LEFT(O56,4))) -> 1793 | Q56: St Austell | R56: St Austell | S56: Cornwall | T56: Unidentified St Austell correspondent (signature not read) to the Earl of Mount Edgcumbe (inferred, Lord Lieutenant) | U56: Magistrate / JP | V56: Lord Lieutenant (forwarded to HO) | W56: =IF(O56="","",INDEX(Lookups!$B$2:$B$56,MATCH(O56,Lookups!$A$2:$A$56,1))) -> Dundas | X56: Food / provisions | Y56: Pre-emptive | Z56: Unclear | AA56: "some Military at Hand" | AB56: N | AI56: Tinners' market price-regulation, Jan 1793 (with Penryn/Bodmin-area corn concealment - Penryn letter 23 Jan f.737). ROUTE: via Lord Lieutenant. CHECK writer and role. Continues Cornwall corn issue (HO42-0053).
A57: HO42-0056 | B57: E47 | C57: Request for troops | D57: N | E57: HO 42/23 | F57: HO-42-23_11.pdf | G57: 65-66 | H57: ff.770-771 | I57: Folio stamp | K57: Digitised (TNA PDF) | L57: Key quote only | M57: "Tho' this part of the Country is now tolerably tranquill, yet as we understand it is the Purpose of the Admiralty to execute Press Warrants, which have been issued, We concur in thinking it highly expedient that the Detachment of the Inniskilling Dragoons should remain here for some Time longer; and we have therefore to request that you will have the Goodness to give the necessary orders for that Purpose. We have much Reason to hope that their Presence will materially contribute to deter the Sailors from attempting to resist an Impress, which they have long threatened." | N57: 11 Mar 1793 | O57: 1793-03-11 | P57: =IF(O57="","",VALUE(LEFT(O57,4))) -> 1793 | Q57: Newcastle upon Tyne | R57: Newcastle upon Tyne | S57: Northumberland | T57: James Rudman (Mayor), John E. Blackett, Jn. Hedley, W. Cramlington, Francis Johnson, Wm Yielder (Aldermen) | U57: Mayor / corporation | V57: Henry Dundas | W57: =IF(O57="","",INDEX(Lookups!$B$2:$B$57,MATCH(O57,Lookups!$A$2:$A$57,1))) -> Dundas | X57: Recruitment / crimping | Y57: Pre-emptive | Z57: Unclear | AA57: Retain detachment of Inniskilling Dragoons | AB57: Y | AI57: Request to KEEP troops, to protect impressment of seamen (war with France from Feb 1793). Follows Tyne seamen's strike (E42).
A58: HO42-0057 | B58: E48 | C58: Request for troops | D58: N | E58: HO 42/35 | F58: HO-42-35_01.pdf | G58: 11-12 | H58: f.11 | I58: Folio stamp | K58: Digitised (TNA PDF) | L58: Key quote only | M58: Copy, Pemberton Milnes, Wakefield 15 Jun 1795: "The general discontent that prevails in the minds of the Manufacturers and common people in this populous part of the Country, is very great, and rather alarming on account of the high price of Corn & other necessaries of Life; presuming the different Corps of Volunteers raised in this Town & others in this neighbourhood, fall within your department... my request is, that you'll be pleased to give orders to the Commanding Officer of such Corps to be ready to aid the Civil Magistrate should they be called upon by him to quell any riotous proceedings". | N58: 15 Jun 1795 | O58: 1795-06-15 | P58: =IF(O58="","",VALUE(LEFT(O58,4))) -> 1795 | Q58: Wakefield | R58: Wakefield | S58: Yorkshire (W. Riding) | T58: Pemberton Milnes | U58: Magistrate / JP | V58: Secretary at War (copy sent to HO) | W58: =IF(O58="","",INDEX(Lookups!$B$2:$B$58,MATCH(O58,Lookups!$A$2:$A$58,1))) -> Portland | X58: Food / provisions | Y58: Pre-emptive | Z58: Unclear | AA58: Orders for local Volunteer corps to aid civil magistrate | AB58: Unclear | AI58: Request to authorise VOLUNTEERS (not regulars) for riot duty - relevant to corps question too. ROUTE: to Secretary at War. Writer role (JP/Deputy Lieutenant) inferred - CHECK.
A59: HO42-0058 | B59: E49 | C59: Request for troops | D59: Y | E59: HO 42/35 | F59: HO-42-35_01.pdf | G59: 35-36, 42 | H59: ff.32-33, 37 | I59: Folio stamp | K59: Digitised (TNA PDF) | L59: Key quote only | M59: Birmingham magistrates to Portland, 23 Jun 1795: "a Detachment of two Troops of the third Regt. of Dragoons having marched to Dudley... at the request of Mr Cartwright and the other Magistrates in that Neighbourhood (who were apprehensive of a Riot amongst the Colliers) a tumultuous assembly collected and attacked a considerable Corn Mill in Snowhill in this Town, under a pretence that the Proprietor Mr Pickard... had been the Means of raising the price of Flour... We then sent to Col. Callow to request him to have the rest of the Troops in readiness... The Riot Act was then twice read... the Peace Officer present found himself under the absolute necessity of directing some of the Party to fire... by which One Man was killed and two wounded... an Express having been sent last Night from Bromsgrove to two of us who are also Magistrates for Worcestershire, for Military assistance... we conceived it expedient to send one Troop for the Protection of that Town and Neighbourhood, there being no Troops either there or at Worcester." | N59: 22-23 Jun 1795 | O59: 1795-06-22 | P59: =IF(O59="","",VALUE(LEFT(O59,4))) -> 1795 | Q59: Birmingham (Snow Hill); Dudley; Bromsgrove | R59: Birmingham | S59: Warwickshire | T59: W. Hicks, R. Spencer, W. Villers (Birmingham magistrates) | U59: Magistrate / JP | V59: Duke of Portland | W59: =IF(O59="","",INDEX(Lookups!$B$2:$B$59,MATCH(O59,Lookups!$A$2:$A$59,1))) -> Portland | X59: Food / provisions | Y59: Actual | Z59: Y | AA59: Local: Dudley JPs requested 2 troops 3rd Dragoons; Birmingham JPs asked Col. Callow to ready remaining troops; Bromsgrove express - 1 troop sent | AB59: Y | AC59: Troops acted locally; riot act read, troops fired (1 killed, 2 wounded); yeomanry (Legge's troop) also used. | AD59: Approved | AH59: Other | AI59: THREE local requests in one letter (Dudley colliers; Birmingham Snow Hill mill riot; Bromsgrove). ROUTE: all local, reported to HO. Seditious handbill circulated next morning, £100 reward. Also Garbett? 23 Jun f.37 and Mordaunt (Walton) 25 Jun f.36 forward Birmingham news. Aston Hall 30 Jun (f.64): peace restored but farmers shy of market.
A60: HO42-0059 | B60: E50 | C60: Request for troops | D60: N | E60: HO 42/35 | F60: HO-42-35_01.pdf | G60: 71-74 | H60: ff.66-69 | I60: Folio stamp | K60: Digitised (TNA PDF) | L60: Key quote only | M60: John Moore, Shardlow 29 Jun 1795: "the lower Order of People inclined to be refractory, are restless and clamorous and we have too much reason to believe they will rise in a Body from the Leicestershire side... there is no Military at Derby - there are at Notting[ha]m... it would be prudent to have a few Horse Soldiers at or near [Shardlow] in case of a disturbance". Forwarded by Sparrow, Bishton 1 Jul: Mr Anson "recommends an application to Government for a party of Horse... Shardlow will accommodate from twelve to twenty Men... The Warehouses at Shardlow always contain property of great value". | N60: 29 Jun - 1 Jul 1795 | O60: 1795-06-29 | P60: =IF(O60="","",VALUE(LEFT(O60,4))) -> 1795 | Q60: Shardlow (Derbyshire), corn warehouses on Trent | R60: Shardlow | S60: Derbyshire | T60: John Moore (Shardlow); fwd by J. Sparrow (Bishton) on behalf of Mr Anson | U60: Private individual | V60: Duke of Portland (via Sparrow) | W60: =IF(O60="","",INDEX(Lookups!$B$2:$B$60,MATCH(O60,Lookups!$A$2:$A$60,1))) -> Portland | X60: Food / provisions | Y60: Pre-emptive | Z60: Unclear | AA60: A party of horse (12-20 men) at Shardlow | AB60: N | AI60: Protection of corn warehouses (inland grain transit). ROUTE: forwarded. Sparrow had also advised application to local magistrates for 'assistance both civil and military'. CHECK writer roles.
A61: HO42-0060 | B61: E51 | C61: Other | D61: Y | E61: HO 42/35 | F61: HO-42-35_02.pdf | G61: 55 | H61: f.127 | I61: Folio stamp | K61: Digitised (TNA PDF) | L61: Key quote only | M61: Gosfield, 9 Jul 1795 (to Portland): "Captain [?] officially reported to me the very gallant & meritorious conduct of Dr John Tolbot of [?], Serjeant in his Yeomanry Troop, & of seven armed yeomen of that town... The crier & bellman of that town having been sent round to give publick notice to the people, to assemble to lower the price of corn, & to pull down the mills; a very considerable mob, to the amount of above 500 people assembled & seized two waggons loaded with wheat, which they began to plunder, but being instantly attacked by these few armed yeomen, the corn was rescued, & escorted by them to the mill... & the mob was dispersed in the course of half an hour." | N61: 9 Jul 1795 | O61: 1795-07-09 | P61: =IF(O61="","",VALUE(LEFT(O61,4))) -> 1795 | Q61: [Essex town near Gosfield - name not read] | R61: [Essex] | S61: Essex | T61: [Lord Lieutenant / Marquess of Buckingham at Gosfield - CHECK] | U61: Lord Lieutenant | V61: Duke of Portland | W61: =IF(O61="","",INDEX(Lookups!$B$2:$B$61,MATCH(O61,Lookups!$A$2:$A$61,1))) -> Portland | X61: Food / provisions | AI61: YEOMANRY used against a food riot (no request to HO). Evidence for corps-against-disorder question. CHECK town name (Halstead/Coggeshall?) and writer; copy sent to Privy Council 11 Jul.
A62: HO42-0061 | B62: E52 | C62: Corps armed/expanded | D62: N | E62: HO 42/35 | F62: HO-42-35_03.pdf | G62: 29 | H62: f.176 | I62: Folio stamp | K62: Digitised (TNA PDF) | L62: Key quote only | M62: Walbrook, 16 Jul 1795: "Yesterday being the weekly Day of Exercise of the Honorable Artillery Company, when the Gentlemen met at their usual Hour... I mentioned to them the Expectations which were entertained of a Riot in that part of the Metropolis and although the Place threatened was not within the limits of the City, they unanimously determined to follow me to any District where the Corps might be of Service, and to remain under Arms to the late Hour of the Night I might think necessary." | N62: 16 Jul 1795 | O62: 1795-07-16 | P62: =IF(O62="","",VALUE(LEFT(O62,4))) -> 1795 | Q62: London (Walbrook) | R62: London | S62: City of London | T62: [Officer/commander of HAC - signature not read] | U62: Volunteer / militia officer | V62: Duke of Portland | W62: =IF(O62="","",INDEX(Lookups!$B$2:$B$62,MATCH(O62,Lookups!$A$2:$A$62,1))) -> Portland | X62: Other / unclear | AI62: Volunteer corps (Honourable Artillery Company) offering riot duty outside the City, Jul 1795 (probably crimping/recruiting-house riots, Jul 1795 - CHECK). CHECK writer.
A63: HO42-0062 | B63: E53 | C63: Request for troops | D63: Y | E63: HO 42/35 | F63: HO-42-35_04.pdf | G63: 50-53 | H63: ff.269-272 | I63: Folio stamp | K63: Digitised (TNA PDF) | L63: Key quote only | M63: Hardwicke (Lord Lieutenant), Wimpole 27 Jul 1795: "unless it is generally known, as a matter of notoriety, that the Magistrates have an opportunity of supporting the authority which the Law has given them, by a military force, capable of intimidating, the County will not think itself secure from the danger of riot & tumult... If therefore a Troop of horse can be spared for the protection of that part of the Country I beg leave to observe that they cannot be more properly stationed than at Wisbech... at Chatteris in the Isle of Ely [a riot] this morning... We can raise troops of Yeomanry Cavalry, having raised a Troop of Fencibles of eighty men at a great expense, which are now sent to a distance, the County has in my opinion a strong claim to military protection". Enclosed, Wisbech JP 25 Jul: canal 'Bankers'... "threatening the principal Farmers, unless they would supply them with bread and mutton at 4 pence per pound, they would pull down their Houses and level them with the Ground... With submission to your Lordship we were safe while Volunteer Norfolk Dragoons were quartered here, but as they are removed the Farmers have every thing to dread from the hands of these Banditti". | N63: 25-27 Jul 1795 | O63: 1795-07-25 | P63: =IF(O63="","",VALUE(LEFT(O63,4))) -> 1795 | Q63: Wisbech & Tydd St Giles (Isle of Ely); Chatteris; Cambridge | R63: Wisbech | S63: Cambridgeshire | T63: Earl of Hardwicke (Lord Lieutenant); enclosing Wisbech magistrate (clergyman) and 12 farmers | U63: Lord Lieutenant | V63: Duke of Portland | W63: =IF(O63="","",INDEX(Lookups!$B$2:$B$63,MATCH(O63,Lookups!$A$2:$A$63,1))) -> Portland | X63: Food / provisions | Y63: Actual | Z63: Y | AA63: A troop of horse, stationed at Wisbech | AB63: N | AC63: Wisbech 3 Aug (HO 42/35_05 f.338): thanks Portland "for the timely and critical Assistance and Protection we received from your Grace's speedy attention to our Lord Lieutenant's kind Requisition for the immediate supply of a Party of Horse"; party of horse with quartermaster arrived Friday afternoon, the day after a riot "with much difficulty dispersed". | AD63: Approved | AE63: 1795-07-31 | AH63: Other | AI63: ROUTE: local magistrate/farmers -> Lord Lieutenant -> HO. Canal labourers ('Bankers') threatening farmers; riots also at Cambridge (Saturday) and Chatteris. KEY: county claims military protection because its own Fencibles were sent away; removal of Norfolk volunteer dragoons left Wisbech exposed. Hardwicke also offers to raise Yeomanry Cavalry.
A64: HO42-0063 | B64: E54 | C64: Request for troops | D64: Y | E64: HO 42/35 | F64: HO-42-35_05.pdf | G64: 72-75 | H64: ff.353-356 | I64: Folio stamp | K64: Digitised (TNA PDF) | L64: Key quote only | M64: Smyth to Lt-Gen Scott (copy), Heath near Wakefield, 6 Aug 1795: "I take the liberty of applying to you to represent the great Disposition to Riot of the Lower Orders of the People in many different parts of this Country, and to suggest the Utility of your sending a Regt. of Dragoons to Wakefield or the Neighbourhood if you can with propriety do so. There are Commotions at Sheffield of the most serious Nature, where some lives have already been lost; a great Riot is now existing at Knottingley near Pontefract where the Volunteers of Wakefield have been sent for... it is greatly apprehended that the Volunteers of the Country tho numerous will be insufficient for the number of places where their Aid may be required... it is important that any troops sent should be steady and well-disciplined men." Covering letter to Portland: "The Riot at Knottingley seems alarming, in order to Places Corn Shipping has been stopp'd & detain'd". | N64: 6 Aug 1795 | O64: 1795-08-06 | P64: =IF(O64="","",VALUE(LEFT(O64,4))) -> 1795 | Q64: Wakefield; Knottingley; Sheffield | R64: Wakefield | S64: Yorkshire (W. Riding) | T64: J. Smyth (magistrate), Heath near Wakefield | U64: Magistrate / JP | V64: Lt-Gen Scott (district commander, Beverley); copy to Duke of Portland | W64: =IF(O64="","",INDEX(Lookups!$B$2:$B$64,MATCH(O64,Lookups!$A$2:$A$64,1))) -> Portland | X64: Food / provisions | Y64: Actual | Z64: Y | AA64: A regiment of dragoons to Wakefield or neighbourhood; 'steady and well-disciplined men' | AB64: Unclear | AI64: ROUTE: to district commander + copy to HO. Volunteers judged insufficient. Knottingley corn-shipping riot; Sheffield commotions with deaths (Aug 1795, volunteers fired - CHECK Sheffield follow-up). Smyth = John Smyth of Heath (MP) - CHECK.
A65: HO42-0064 | B65: E55 | C65: Other | D65: N | E65: HO 42/35 | F65: HO-42-35_05.pdf | G65: 85-87 | H65: ff.366-368 | I65: Folio stamp | K65: Digitised (TNA PDF) | L65: Key quote only | M65: Woodstock area, 7 Aug 1795 (to Portland, re Oxfordshire): "on Wednesday the Inhabitants of Witney seized some grain as it was going to be sent out of the Country, brought it back to Witney and sold it at a low price - The lower class of People now say that since soldiers were sent into this Country and the Duke of Portland's letter to the Duke of Marlborough Farmers & Jobbers dare demand double the price... it was mentioned that the Magistrates imagined Government meant to enforce the removal of Grain from this Country by the Military, as soldiers were sent without the application or even the knowledge of [the magistrates]". | N65: 7 Aug 1795 | O65: 1795-08-05 | P65: =IF(O65="","",VALUE(LEFT(O65,4))) -> 1795 | Q65: Witney / Woodstock | R65: Witney | S65: Oxfordshire | T65: [Oxfordshire magistrate - signature not read] | U65: Magistrate / JP | V65: Duke of Portland | W65: =IF(O65="","",INDEX(Lookups!$B$2:$B$65,MATCH(O65,Lookups!$A$2:$A$65,1))) -> Portland | X65: Food / provisions | AI65: KEY: troops SENT WITHOUT REQUEST to Oxfordshire in 1795 (cf. Bend on Oxford 1800) - magistrates suspect troops are there to enforce grain removal. Use for 'unrequested deployment' check. Writer CHECK.
A66: HO42-0065 | B66: E54 | C66: Corps armed/expanded | D66: Y | E66: HO 42/35 | F66: HO-42-35_06.pdf | G66: 18-19, 51 | H66: ff.385-386, 414 | I66: Folio stamp | K66: Digitised (TNA PDF) | L66: Key quote only | M66: Sheffield, 11 Aug 1795 (to Portland): "there is very little Effect in Suppression of the Riot to be attributed to any Exertion of mine. The Zealous firm & determined Conduct & Activity of Col. Athorpe & his Regt. of Volunteers and of the Officers & Men of the Cavalry secured our Success at that Time of Alarm when it was necessary to appear in Force". Saville Row 9 Aug (f.414): "the necessity of removing Colonel Cameron's Regiment from Sheffield was yesterday communicated from Mr Dundas's Office to the Quarter Master General, and... an order was sent by Post for their March from thence." | N66: 9-11 Aug 1795 | O66: 1795-08-04 | P66: =IF(O66="","",VALUE(LEFT(O66,4))) -> 1795 | Q66: Sheffield | R66: Sheffield | S66: Yorkshire (W. Riding) | T66: [Sheffield magistrate - signature not read]; Saville Row letter signed [Brownrigg?] | U66: Magistrate / JP | V66: Duke of Portland | W66: =IF(O66="","",INDEX(Lookups!$B$2:$B$66,MATCH(O66,Lookups!$A$2:$A$66,1))) -> Portland | X66: Food / provisions | AI66: Sheffield riot of 4 Aug 1795 (soldiers of Col. Cameron's newly raised regiment over pay/bounty, joined by townspeople; Volunteers under Col. Athorpe fired, deaths). VOLUNTEER CORPS USED TO SUPPRESS RIOT; regulars (Cameron's) then REMOVED from town as a cause of disorder. Same episode as Wakefield/Knottingley (E54). CHECK riot details and writer.
A67: HO42-0066 | B67: E56 | C67: Request for troops | D67: Y | E67: HO 42/36 | F67: HO-42-36_02.pdf | G67: 71-72 | H67: ff.121-122 | I67: Folio stamp | K67: Digitised (TNA PDF) | L67: Key quote only | M67: Henry Cholmley, Howsham, 15 Nov 1795 (to Portland): "Stocks [of corn] from the interior part of the Country [are] totally shut up... which publication although not signed, has intimidated the Farmers from transporting their Corn, and the Sellers from buying... I have this moment heard that the Military from York have just passed my Door in great haste to aid the Magistrates at Whitby... it leads me to request your Grace will desire the Secretary at War, if not extremely inconvenient to the Service, that at least one Troop may be stationed there, as I have it from the first Authority (the principal Inhabitants of Whitby) that the Volunteers have lost the Confidence of the People, and that little Reliance can be had on that body, the one half of them being Republicans at Heart... the lower Class of people are as bad as a Nest of Hornets". | N67: 15 Nov 1795 | O67: 1795-11-15 | P67: =IF(O67="","",VALUE(LEFT(O67,4))) -> 1795 | Q67: Whitby (letter from Howsham) | R67: Whitby | S67: Yorkshire (N. Riding) | T67: Henry Cholmley | U67: Private individual | V67: Duke of Portland | W67: =IF(O67="","",INDEX(Lookups!$B$2:$B$67,MATCH(O67,Lookups!$A$2:$A$67,1))) -> Portland | X67: Food / provisions | Y67: Actual | Z67: Y | AA67: At least one troop stationed at Whitby | AB67: Y | AI67: KEY: VOLUNTEERS UNRELIABLE ('Republicans at Heart') - reason for requesting regulars. Military from York already marching to aid Whitby magistrates (separate, earlier request not seen). Corn shipping riots at Whitby Nov 1795 - CHECK HO 42/36-37 for Whitby magistrates' own letters. Writer role (landowner/JP?) - CHECK.
A68: HO42-0067 | B68: E57 | C68: Request for troops | D68: Y | E68: HO 42/36 | F68: HO-42-36_03.pdf | G68: 69-70 | H68: ff.202-203 | I68: Folio stamp | K68: Digitised (TNA PDF) | L68: Key quote only | M68: Hardwicke, Wimpole 18 Sep 1795: "a Riot which took place at Ely on Tuesday last, on account of the scarcity & high price of Provisions. I am informed by a Letter from the Magistrates, that another is expected tomorrow, the Market day. They are very anxious to have some troops for the protection of the Place, & the preservation of the Peace, and applied to me to know if I thought they had a right to demand the assistance of some Cavalry now stationed at Mildenhall, within six miles of Ely. As that place is in Suffolk, I told them it did not appear to me they had any right to call upon the officer to assist them, though I hope your Grace will give them that power, if the Cavalry remains at Mildenhall... the extraordinary Listlessness & apathy, which I am sorry to say pervades this County, and has hitherto rendered every attempt to raise Volunteer Yeomanry Cavalry ineffectual." | N68: 18 Sep 1795 | O68: 1795-09-18 | P68: =IF(O68="","",VALUE(LEFT(O68,4))) -> 1795 | Q68: Ely (Isle of Ely) | R68: Ely | S68: Cambridgeshire | T68: Earl of Hardwicke (Lord Lieutenant), for Ely magistrates | U68: Lord Lieutenant | V68: Duke of Portland | W68: =IF(O68="","",INDEX(Lookups!$B$2:$B$68,MATCH(O68,Lookups!$A$2:$A$68,1))) -> Portland | X68: Food / provisions | Y68: Actual | Z68: Unclear | AA68: Authority to call cavalry stationed at Mildenhall (Suffolk), 6 miles away | AB68: Y | AI68: KEY: troops 6 miles away but across county line - magistrates had no right to call them without HO authority. Illustrates jurisdictional limit on local requisitions. Also: county apathy has defeated attempts to raise Yeomanry Cavalry.
A69: HO42-0068 | B69: E58 | C69: Other | D69: N | E69: HO 42/36 | F69: HO-42-36_03.pdf | G69: 40-41 | H69: ff.178-179 | I69: Folio stamp | K69: Digitised (TNA PDF) | L69: Key quote only | M69: "my apprehensions respecting the Rioting of the Miners (of which I had the honor of mentioning to you in a former Letter) is now almost come to a Crisis... I have, and will, do every thing in my power to keep them quiet but I am afraid all will be fruitless unless something is done to lower the price of Corn soon". | N69: 5 Nov 1795 | O69: 1795-11-05 | P69: =IF(O69="","",VALUE(LEFT(O69,4))) -> 1795 | Q69: Harewood [Cornwall?] | R69: Harewood | S69: [CHECK] | T69: J. H. Foote(?) | U69: Magistrate / JP | V69: Home Office (Under-Secretary) | W69: =IF(O69="","",INDEX(Lookups!$B$2:$B$69,MATCH(O69,Lookups!$A$2:$A$69,1))) -> Portland | X69: Food / provisions | AI69: Miners threatening riot over corn prices; enclosure from mine captain. No explicit troop request on these pages. CHECK location (Harewood near Calstock, Cornwall/Devon border?) and writer; earlier letter referred to.
A70: HO42-0069 | B70: E59 | C70: Request for troops | D70: N | E70: HO 42/37 | F70: HO-42-37_04.pdf | G70: 92-93 | H70: ff.306-307 | I70: Folio stamp | K70: Digitised (TNA PDF) | L70: Key quote only | M70: "A great many Women supported by a number of other persons had for some days past in the most riotous manner prevented the Shipping of Flour for the Capital... I previously order'd a Company of the Pembroke Militia from Holt to Warham about a Mile distant to wait for Orders - Upon our arrival at Wells, after Mr Hoste had twice warned them... and having twice read the Proclamation, amidst Clamour and Menaces, I order'd the Company of the Pembrokeshire to march in, whose behaviour was equally Active, as prudent, after driving the Mob off with Bayonets they secured and protected the Flour and Ship". | N70: 16 Dec 1795 | O70: 1795-12-14 | P70: =IF(O70="","",VALUE(LEFT(O70,4))) -> 1795 | Q70: Wells (next the Sea) | R70: Wells-next-the-Sea | S70: Norfolk | T70: Marquis Townshend (Lord Lieutenant), with Rev. Mr Hoste (JP) | U70: Lord Lieutenant | V70: Duke of Portland | W70: =IF(O70="","",INDEX(Lookups!$B$2:$B$70,MATCH(O70,Lookups!$A$2:$A$70,1))) -> Portland | X70: Food / provisions | Y70: Report only | Z70: Y | AA70: A company of Pembrokeshire Militia from Holt (ordered locally by Lord Lieutenant) | AB70: Y | AC70: Militia drove crowd off with bayonets; flour shipped; Coke and magistrates settled poor allowances. | AD70: Approved | AH70: Other | AI70: ROUTE: Lord Lieutenant ordered nearby militia himself; reported to HO. Women-led riot against flour shipping to London. Date of riot approx. (several days before 16 Dec).
A71: HO42-0070 | B71: E59 | C71: Request for troops | D71: Y | E71: HO 42/37 | F71: HO-42-37_04.pdf | G71: 96-97 | H71: ff.308-309 | I71: Folio stamp | K71: Digitised (TNA PDF) | L71: Key quote only | M71: "the Evil is increasing since I had the honor to inform your Grace of what had pass'd at Wells; in those parts where there is Yeomanry Corps they are quiet. I have however desired them to be prepared in their several Hundreds as from such examples the total communication of this County with the Sea Ports may be intercepted - It may be necessary to alter the Quarters of Troops according to Circumstances, & if a Detachment of some Light Cavalry, or of the Horse Artillery could be stationed on the Coast, I conceive it would be of great service, for the Military at Norwich should not be too much weakened... If the Evil increases, I request the Orders of Government". | N71: 22 Dec 1795 | O71: 1795-12-22 | P71: =IF(O71="","",VALUE(LEFT(O71,4))) -> 1795 | Q71: Norfolk coast (letter from Raynham) | R71: [North Norfolk coast] | S71: Norfolk | T71: Marquis Townshend (Lord Lieutenant) | U71: Lord Lieutenant | V71: Duke of Portland | W71: =IF(O71="","",INDEX(Lookups!$B$2:$B$71,MATCH(O71,Lookups!$A$2:$A$71,1))) -> Portland | X71: Food / provisions | Y71: Pre-emptive | Z71: Unclear | AA71: Detachment of light cavalry or horse artillery stationed on the coast | AB71: Y | AI71: KEY: 'where there is Yeomanry Corps they are quiet' - yeomanry as deterrent. Also asks Admiralty to deal with sailors joining commotions in sea-port towns.
A72: HO42-0071 | B72: E60 | C72: Request for troops | D72: N | E72: HO 42/37 | F72: HO-42-37_04.pdf | G72: 100-108 | H72: ff.310-314 | I72: Folio stamp | K72: Digitised (TNA PDF) | L72: Key quote only | M72: Jodrell, Bayfield 22 Dec 1795 (to Townshend): "in consequence of the Requisition of Mr Collyer & myself Major Genl Leland dispatched Cornet Bower with Thirty of the Inniskillen Dragoons, who reached Holt early on the same Morning... a Mob intended to assemble & take away the Flour which was left at the Publick House on Sherrington Common... I sent out Notices to the High Constables of the Hundred... the Farmers & the Yeomanry of the different Parishes to assemble... nearly 300 respectable Farmers & Yeomanry". Townshend 23 Dec: "the Farmers and others of Property are forming such an Association in support of the Civil Power as will in some degree supply the defect of a Corps of Yeomanry... I have consented to a small Detachment of Cavalry continuing at Holt till this body is form'd". | N72: 20-23 Dec 1795 | O72: 1795-12-20 | P72: =IF(O72="","",VALUE(LEFT(O72,4))) -> 1795 | Q72: Holt / Sheringham Common | R72: Holt | S72: Norfolk | T72: H. Jodrell & Mr Collyer (JPs); fwd by Marquis Townshend | U72: Magistrate / JP | V72: Maj-Gen Leland (requisition); report to Townshend, fwd to Portland | W72: =IF(O72="","",INDEX(Lookups!$B$2:$B$72,MATCH(O72,Lookups!$A$2:$A$72,1))) -> Portland | X72: Food / provisions | Y72: Actual | Z72: Unclear | AA72: Requisition to Maj-Gen Leland: 30 Inniskilling Dragoons sent | AB72: Y | AC72: 30 dragoons sent by district general; ringleader taken; ~300 farmers and yeomen assembled; flour forwarded to Lynn. | AD72: Approved | AH72: Other | AI72: ROUTE: local requisition to district general. ALSO A CORPS EVENT: farmers forming an 'Association in support of the Civil Power' to substitute for missing yeomanry - KEY QUOTE for corps question.
A73: HO42-0072 | B73: E61 | C73: Request for troops | D73: N | E73: HO 42/37 | F73: HO-42-37_05.pdf | G73: 38-39 | H73: f.354 | I73: Folio stamp | K73: Digitised (TNA PDF) | L73: Key quote only | M73: Townshend, Yarmouth 4 Dec 1795: "the Barracks which had been badly smash'd, by the Huntingdon especially, and all would have been demolished but by the activity of the Officers, and Sir Thos Hyde Page, and Captain Hook of the Artillery who directed several Pieces of Ordnance upon the Rioters... a second violence was intended but the arrival of the two Troops of the Inniskilling Dragoons from Norwich and the vigilance of the Artillery prevented it. Their pretence was the shutting the Barrack Gates an hour sooner... it is imputed to their frequenting low Alehouses where they are instigated by the Dissenters of which there are many in the Regiment". Militia at Norwich, the Cambridge especially, expressed readiness to suppress the outrage. | N73: 4 Dec 1795 | O73: 1795-12-03 | P73: =IF(O73="","",VALUE(LEFT(O73,4))) -> 1795 | Q73: Great Yarmouth (barracks) | R73: Great Yarmouth | S73: Norfolk | T73: Marquis Townshend (Lord Lieutenant) | U73: Lord Lieutenant | V73: Duke of Portland | W73: =IF(O73="","",INDEX(Lookups!$B$2:$B$73,MATCH(O73,Lookups!$A$2:$A$73,1))) -> Portland | X73: Other / unclear | Y73: Report only | Z73: Unclear | AA73: 2 troops Inniskilling Dragoons from Norwich (called in); artillery turned guns on rioters | AB73: Y | AI73: MILITIA MUTINY/RIOT (Huntingdonshire Militia attacking Yarmouth barracks) - troops used against troops. Requester of dragoons not stated (probably local commanders) - CHECK. Relevant to militia reliability and to barracks as flashpoints.

Sheet Leads
A1: Lead ID | B1: Event type | C1: Place | D1: County | E1: Date (ISO) | F1: Summary | G1: Archive ref (as cited) | H1: Cited by | I1: Verified in original? | J1: Priority | K1: Notes / conflicts
A2: L001 | B2: Request for troops | C2: Oxford | D2: Oxfordshire | E2: 1800-09-04 | F2: Troops (11th Light Dragoons) sent to Oxford; town clerk protests on behalf of volunteers; HO reply reassures them. | G2: HO 42/51 ff.36-7, 59-60; HO 50/388; HO 43/12 pp.106-7 (King to Taunton, 8 Sep 1800) | H2: Bend 2018; Gee (via other session) | I2: N | J2: High | K2: CONFLICT: Gee says Vice-Chancellor requested troops; Bend says Portland sent them unrequested on Rev. D. Hughes's letter, V-C later asked they stay. Other session dated the reply 1801 - wrong, it is 1800.
A3: L002 | B3: Request for troops | C3: Banbury | D3: Oxfordshire | E3: 1800 | F3: Mayor wants "soldiers unconnected with the place" because yeomanry sympathised with rioters. | G3: HO 42/51 f.116 | H3: Gee (via other session) | I3: N | J3: High | K3: Local force distrusted - fits "civil power inadequate".
A4: L003 | B4: Request for troops | C4: Birmingham | D4: Warwickshire | E4: 1800-11 | F4: Troops sent on Lord Lieutenants' information without consulting magistrates, who objected. | G4: HO 43/12 pp.313-6; HO 42/53 ff.404-5 | H4: Bend 2018 | I4: N | J4: Medium | K4: Deployment WITHOUT request - code as unrequested, not as request.
A5: L004 | B5: Other | C5: Berkeley | D5: Gloucestershire | E5: 1800-09-16 | F5: Earl of Berkeley: restraint in sending for soldiers "till... absolutely necessary"; cross-county correspondence rumoured. | G5: HO 42/51 ff.168-9 | H5: Bend 2018 | I5: N | J5: Low | K5: Evidence of reluctance to request.
A6: L005 | B6: Corps armed/expanded | C6: Henley | D6: Oxfordshire | E6: 1800 | F6: Anonymous threat leads to armed-association patrols. | G6: HO 42/49 f.393 | H6: Gee (via other session) | I6: N | J6: Medium
A7: L006 | B7: Corps armed/expanded | C7: Hambledon & Wickham | D7: Hampshire | E7: 1800-03 | F7: Volunteers kept in constant readiness against grain-price disorder; Lt-Col Palmer seeks pay for nightly patrols; WO objects only to pay. | G7: HO 50/48 ff.153, 165, 209, 246 | H7: Gee (via other session) | I7: N | J7: Medium | K7: Money for internal-order duty.
A8: L007 | B8: Request for troops | C8: Stony / Fenny Stratford | D8: Buckinghamshire | E8: 1796-03-25 | F8: Newport & Buckingham Yeomanry in riot context. | G8: HO 50/330 (Nugent [Buckingham], 25 Mar 1796) | H8: Gee (via other session) | I8: N | J8: High | K8: Check whether this is a request or a report.
A9: L008 | B9: Request for troops | C9: Tavistock | D9: Devon | E9: 1801-03-14 | F9: Riot-related correspondence. | G9: HO 50/49 (Bray to Dundas, 14 Mar 1801) | H9: Gee (via other session) | I9: N | J9: High
A10: L009 | B10: Other | C10: Sheffield | D10: Yorkshire (W. Riding) | E10: c.1800-01 | F10: Reliability enquiries on the corps; HO advises not to call it on active duty. | G10: HO 50/49 | H10: Gee (via other session) | I10: N | J10: Medium | K10: A government response on corps reliability.
A11: L010 | B11: Corps founded | C11: Kettering & Rothwell | D11: Northamptonshire | E11: 1798-05-25 | F11: Associations recommended to the Lord Lieutenant "entirely in terms of their usefulness against disturbances" after 1795 Kettering food riot. | G11: HO 50/42 (James Curry to Earl of Northampton) | H11: Gee (via other session) | I11: N | J11: Medium | K11: Key-quote candidate.
A12: L011 | B12: Corps founded | C12: Hampshire (county) | D12: Hampshire | E12: 1794-06-11 | F12: Plan for a county-wide "Association for assisting the Civil Power" to suppress seditious tumults at magistrates' call. | G12: Hampshire RO 65 M 85/1 | H12: Gee (via other session) | I12: N | J12: Medium | K12: Key-quote candidate. County record office, not TNA.
A13: L012 | B13: Corps armed/expanded | C13: Windsor | D13: Berkshire | E13: 1803-08 | F13: Magistrates, after repeated riots, request leave to levy an additional troop of fencible cavalry. | G13: Berkshire RO D/ERa O8/2 (5) | H13: Gee (via other session) | I13: N | J13: Low | K13: 1803 - outside 1790s window; confirm period with JV.
A14: L013 | B14: Corps armed/expanded | C14: Hampton Lucy | D14: Warwickshire | E14: 1807-10-07 | F14: Volunteers' unauthorised paid permanent duty allowed though "irregular". | G14: HO 51/86 (Hawkesbury to Warwick) | H14: Gee (via other session) | I14: N | J14: Low | K14: 1807 - outside window.
A15: L014 | B15: Other | C15: National | D15: - | E15: 1797-04 | F15: Draft circular: volunteer/yeomanry COs to help magistrates apprehend persons in treasonable proceedings (June 1797 proclamation). | G15: HO 50/55 | H15: Gee (via other session) | I15: N | J15: Medium | K15: Policy context.
A16: L015 | B16: Other | C16: National | D16: - | E16: 1798-03-05 | F16: Dundas circulars proposing armed associations to relieve regulars in "the preservation of internal tranquillity and the maintenance of a proper police". | G16: Worcs RO BA 2868/4 705:73 (Dundas to Coventry, 5 Mar & 6 Apr 1798) | H16: Gee (via other session) | I16: N | J16: Medium | K16: Key-quote candidate (government rationale).
A17: L016 | B17: Request for troops | C17: London | D17: Middlesex / City | E17: 1794-08 to 1800-09 | F17: London & Westminster Light Horse Volunteers called out or on readiness at least 26 times, half in 1795; requests from Lord Mayor and police magistrates. | G17: PRO 30/3/2 (list of correspondence); PRO 30/3/25 (CO's reports) - Bosanquet Papers | H17: Gee (via other session) | I17: N | J17: High | K17: Best run of request + response in one place. Includes our log rows HO42-0014 and HO42-0017.
A18: L017 | B18: Request for troops | C18: London | D18: Middlesex | E18: 1795-06-28 | F18: HO directs Lord Mayor to request metropolitan corps before LCS meetings; HO requests LHV and St James's Association directly (1795-97). | G18: HO 65/1 (Portland to Lord Mayor 28 Jun 1795; King to Herries 24 Oct 1795; Portland to St James's Assoc. 28 Jul 1797) | H18: Gee (via other session) | I18: N | J18: Medium | K18: Requests initiated by HO, not by locality - code separately.
A19: L018 | B19: Other | C19: England (food riots) | D19: - | E19: 1793-1801 | F19: Wells tabulates 202 food disturbances with force used (volunteers 86, regulars 62, both 26). | G19: Wells, Wretched Faces, pp.419-440 | H19: Gee (via other session) | I19: N | J19: High | K19: Candidate riot denominator. Get the table.
A20: L019 | B20: Other | C20: Tavistock | D20: Devon | E20: 1794-05-29 | F20: F. Buller forwards letter from Mr Carter JP on "disturbances amongst the woolcombers", which "will not be confined to Tavistock". | G20: HO 42/30 f.324 (covering letter); enclosure not found at f.325 | H20: HO 42 read 7 Oct 2026 | I20: Partly | J20: Medium | K20: Enclosure missing - may be a request; search nearby folios / HO 43/5 for reply c. 30 May 1794.
A21: L020 | B21: Other | C21: Littlehampton (nr Arundel) | D21: Sussex | E21: 1794-08-24 | F21: Informant: privates of the Oxford and Surrey militia regiments in cantonment there said during the winter "they would join the French if they landed" and "should live better" in that case; landlord says disaffection general. | G21: HO 42/33 f.255 | H21: HO 42 read 7 Oct 2026 | I21: Y | J21: Low | K21: Militia reliability (context for Q5 and for why regulars were requested). Not a request or corps event.
... A28: L027 | B28: Other | C28: England (county returns) | D28: [Multiple] | E28: 1795-11 | F28: Magistrates' returns to Portland's Oct-Nov 1795 circular on the 1795 harvest: crop yields (wheat, barley, oats, pease) by hundred/parish vs average years, for many counties (Cornwall, Devon, Northants, Lancashire, Kent, Surrey, Middlesex...). | G28: HO 42/36_01 ff.1-66 (and probably further 36_ files) | H28: HO 42 read 30 Oct 2026 | I28: Y | J28: Medium | K28: Possible HARVEST-SHORTFALL data by locality (Nov 1795) - a candidate control variable for JV. Not events.

Sheet Legend
A1: HO 42 extraction log - legend & conventions
A3: Purpose | B3: Log events in HO 42 (Home Office domestic correspondence) for the Voth/UBS project.
A4: Priority | B4: Requests for troops are ~10x more important than granting decisions (per JV). Barracks: in scope. Corps founded/armed (esp. 'to suppress Insurrections'): key quotes.
A5: Responses | B5: HO 43 (Home Secretary's replies) is NOT digitised and not in these PDFs; response columns (K-O) are blank unless a docket/endorsement appears in HO 42 itself. Treat as descriptive background only.
A6: Geography | B6: England only. Wales and Scotland are out of scope (per JV) - do not log.
A8: Event type (controlled vocabulary)
A9: Request for troops | B9: Civil magistrate/corporation asks government for regular troops, militia or military aid against disturbance/insurrection.
A10: Corps founded | B10: A new volunteer/militia/armed-association corps raised (offer, resolutions, or King's approbation).
A11: Corps armed/expanded | B11: Existing corps seeking or granted more men, arms, field pieces or funding.
A12: Barracks | B12: Request to build or site barracks (often riot/internal-order driven).
A13: Corps forming (context) | B13: Mentions that associations/corps are being raised, without a discrete offer document.
A15: Column groups
A16: ID / triage (grey) | B16: Row ID, Episode ID, Event type, Key quote?
A17: Source (blue) | B17: Call number, File, PDF page, Folio, Folio basis, Link, Image status
A18: Text (yellow) | B18: Transcription status, key quote
A19: Where / when (green) | B19: Dates, place, county (England only)
A20: Who (orange) | B20: Writer, role, addressee, Home Secretary in office
A21: Request detail (red) | B21: Fill for requests and barracks rows: disturbance, request kind, civil power inadequate, force requested, military nearby
A22: Response (grey) | B22: HO 43 / dockets - background only
A24: Column notes | B24: Hover over any header in Events for its definition. Dropdown values live on the Lookups sheet; add new values there.
A25: Folio vs PDF page | B25: TNA HO 42 PDFs were made from microfilm before a later re-foliation. Record the stamped folio AND the PDF page; set Folio basis. Existing rows marked "Unclear - check".
A26: Dates | B26: Date (ISO) is typed as text YYYY-MM-DD - Excel cannot hold pre-1900 dates. Year and Home Secretary are formulas off it.
A27: Episodes | B27: One episode = one incident. Several letters about the same riot share an Episode ID. The regression unit is likely the episode, not the letter.
A28: Auto-filled fields | B28: Episode, county, role, disturbance, request kind, civil power, force, military nearby were filled from the existing quotes and notes on 7 Oct 2026 - verify against the letters. Uncertain cases flagged "CHECK:" in Notes.
A30: Coverage of this draft
A31: Fully read -> rows derived | B31: HO 42/16 (01-05); HO 42/34 (01-05); HO 42/30_01; HO 42/33 (01-03) - read folio-by-folio.
A32: Coverage - status (7 Oct 2026) | B32: HO 42/30_02-05: now read in full (30_03 ff.156-184; 30_04 ff.204-261; 30_05 ff.280-334 completed this session). New rows: HO42-0018 Birmingham cavalry (30_04 ff.225-7), HO42-0019 Doncaster internal defence (30_05 f.333). Out of scope noted: Kirkwall barracks petition (30_03 ff.160-4, Scotland), Wrexham riot note (30_04 f.226, Wales), Dumfries (30_05 f.323, Scotland). HO 42/33_05 ff.369-376 now read: new row HO42-0020 Kenninghall/Harling request (ff.369-70). HO 42/33_04 ff.234-295 now read: no new rows (crimp-riot follow-ups added to HO42-0014 notes; militia disaffection at Littlehampton added to Leads). ALL GAP FILES NOW READ IN FULL. | 26 Oct 2026: HO 42/19_01 and 19_02 read in full (rows HO42-0021 to 0023, Priestley riots). | HO 42/19_03 read in full (Wolverhampton, Bristol, Leicester requests; Coventry thanks 22 Jul f.244 - troops' 'appearance has had the desired effect'). | HO 42/19_04 read in full (Sheffield enclosure-riot request; Bristol and Oxford follow-ups). | HO 42/19_05 read in full (mostly King's Bench depositions on Birmingham rioters; Sheffield request to keep troops). | HO 42/19_06 read in full: no events (Birmingham prosecution papers, handbills, depositions, list of prisoners). | HO 42/19_07 read in full: no events (Birmingham informations/depositions, prosecution correspondence, seditious placard 9 Aug 1791). | HO 42/19_08 read in full (Snitterfield and Raynham associations; Sheffield 25 Aug enclosure still opposed, military 'stationed here'; Bristol 10 Sep troops released). | HO 42/19_09 read in full: no new events (Birmingham depositions, Berwick convict, Dundas reply to Orford re Norfolk association added to HO42-0030). | HO 42/19_10 read: no events (King's Bench affidavits, petitions, Dutch/Irish business, Nov-Dec 1791). HO 42/19 COMPLETE. | HO 42/20_1 (Jan-Mar 1792) read: no events (convict/gaol business, pardons, Dutch frigate wreck at Coverack 1791 with plundering - context only, Cambridge degrees). | HO 42/20_2 (Mar 1792) read: no events (pamphlet on magistrates/police, convicts, Norwich United Constitutional Societies resolutions 24 Mar 1792 - context). | HO 42/20_3 (Mar-May 1792; also Liverpool letters to Oct 1792) read: 3 Liverpool/Wigan requests (labour disputes). | HO 42/20_4 (May 1792) read: Sheffield, Birmingham, Leeds requests; also Manchester radical-society surveillance (f.275), Bristol 1792. | HO 42/20_5 (May-Jun 1792) read: Mount Street riots (troops called locally). Context: replies to 21 May proclamation circular; 13 Jun report on disaffection in 2nd Dragoons at Manchester (f.386). | HO 42/20_6 (Jun 1792) read: no events (Prussia Cove smuggling, proclamation addresses, Lancaster gaol plot, police magistrate appointments). | HO 42/20_7 (Jun-Sep 1792) read: 1792 barracks programme (Sheffield, Manchester, Nottingham, Birmingham) with plans and costs; 2nd Dragoons combination at Manchester. HO 42/20 COMPLETE. | HO 42/21_01 (Jul 1792) read: Coventry barracks site plan; otherwise proclamation addresses, appointments, Paine pamphlet. | HO 42/21_02 (Jul 1792) read: no events (police magistrate appointments under Middlesex Justices Act, proclamation addresses, convicts, Hague dispatch). | HO 42/21_03 read: no events. HO 42/21_04 (Aug 1792) read: Kingswood/Somerset colliers' strike - Camerton troops (local request), Bristol report. | HO 42/21_03 (late Jul-Aug 1792) read: no events (police magistrate/clerk appointments, petitions, Durham county meeting on proclamation). | HO 42/21_05 (Aug-Sep 1792) read: no events (finance proposals, Warwick gaol plot, Nootka furs, Irish intelligence, Kent/Cumberland felon lists). | HO 42/21_06 (Sep 1792) read: Coventry barracks letters/plans added to HO42-0042; otherwise French emigre priests arriving (Eastbourne, Portsmouth), Nootka, appointments. | HO 42/21_07 (Sep 1792) read: no events (emigre priests Portsmouth/Jersey, convicts, Manchester handbills, Suffering Clergy committee). | HO 42/21_08 (late Sep 1792) read: no events (emigres, Preston combination convicts' petition, Stockport radical society papers). HO 42/21 COMPLETE. | HO 42/22_01 (1-3 Oct 1792) read: Wigan original requests (Campbell refused without Sec of State orders); Norwich barracks; also James Maxwell re brother Dr Maxwell (radical), emigres. | HO 42/22_02 (3-14 Oct 1792) read: DeLancey barracks programme report (f.156); Nepean enquiry re arms from Birmingham/Sheffield sent to Ireland (f.135, context); emigres; convicts. | HO 42/22_03 (15-30 Oct 1792) read: Leicester (to Sec at War) and Yarmouth (local requisition) requests; Brooke (Birmingham) re Dr Maxwell's dagger pattern (f.166); Anglesey seditious sermon (Bulkeley); Privy Council business lists. | HO 42/22_04 (late Oct-5 Nov 1792) read: Yarmouth sailors' and food riots (added to HO42-0049); North Shields seamen's strike; Ashby canal; Duke of Brunswick effigy plan (Southwark, informer). | HO 42/22_05 (5-11 Nov 1792) read: Newcastle magistrates' request + response (Tyne seamen); Yarmouth printed address; Durham/Bishop of Durham letters; Methodist pamphlet. | HO 42/22_06 (10-17 Nov 1792) read: Ipswich Ante-Levelling Society; Townshend 11 Nov on King's Lynn sailors' strike and Yarmouth riots ('the power they have to call on the Military when necessary'); South Shields 13 Nov riot ending, dragoons stopped at Durham; Nepean to DeLancey 13 Nov re Tynemouth Barracks force; Newcastle 14 Nov. | HO 42/22_07 (17-23 Nov 1792) read: no new rows (Stisted/Ipswich riot added to HO42-0052; Newcastle/Shields aftermath; Bristol printed resolutions; London debating society; Scots Brigade memorial). | HO 42/22_08 (23-27 Nov 1792) read: no new rows (Tyne aftermath, Norfolk radical clubs report, Liverpool reform association advert, county replies to 24 Nov circular on seditious writings). | HO 42/22_09 (28-30 Nov 1792) read: no new rows (S. Shields ship-owners criticise magistrates - added to HO42-0051; peace officers suggestion; Yarmouth seditious song; county replies to circular; Frenchmen with daggers at Chelmsford). HO 42/22 COMPLETE. | HO 42/23_01 (22 Nov-3 Dec 1792) read: no new rows (Newcastle 2 Dec sailors/press, added to HO42-0051; replies to sedition circular; Thetford-area/Portsmouth soldier rumours; Ayr; informer reports on Frenchmen). | HO 42/23_02 (3-6 Dec 1792) read: no new events (militia embodiment returns, Chelmsford foreigners, Arundel soldiers' pay, Yorkshire militia substitutes - 2 leads added). | HO 42/23_03 (6-7 Dec 1792) read: no new events (Salisbury: 'appearances of rising' in villages over scarcity of spinning work - handled by talking to manufacturers, no troops; Birmingham 10,000 daggers order for Dr Maxwell; Flintshire assignats; informers; Treaty with Dorset re Dover). | HO 42/23_04 (7-10 Dec 1792) read: no new Events rows (Birmingham Dec riot lead and Guards' disaffection lead added; Canterbury Kentish Gazette; Liverpool loyal address; emigrants arriving; Wycombe loyal; reform society toasts). | HO 42/23_05 (10-14 Dec 1792) read: Cornwall miners/corn export (HO42-0053, contingent); Newcastle pitmen Feb 1793 report misfiled (lead); London defence plan (ff.334-338, Guards/cavalry dispositions, context); Birmingham arms informer; Leigh (Kent) sedition. | HO 42/23_06 (14-18 Dec 1792) read: no new Events rows (Manchester Church-and-King riot lead; Molesworth original f.387; Chatham sedition examinations; emigrants). | HO 42/23_07 (18-22 Dec 1792) read: no events (petitions, informers on French/Jacobins, Univ. Society Friends of the People declaration, Debtors' relief, arrivals of French at Dover/Portsmouth, Chelsea sedition). | HO 42/23_08 (23-27 Dec 1792) read: Grenfell coastal corps proposal (HO42-0054); 'Birmingham waggon' to Dover suspected of carrying arms to France (f.505, context); informers on Jacobins; Chatham Barracks recruiting; French arrivals. | HO 42/23_09 (27-31 Dec 1792) read: no events (French arrivals at ports, Ramsgate warlike stores to France, convict petitions, Carlisle, Lancashire dissenting meeting-house lists, printed handbills). | HO 42/23_10 (undated 1792 items) read: no events (London radical clubs/foreigners intelligence, Redruth tinners loyal 'God save the King - down with the Methodists', anonymous riot letter, Scotch Brigade memorial, petitions). | HO 42/23_11 (Jan-Mar 1793, misc.) read: St Austell tinners (Jan 1793) and Newcastle impress requests; Bristol/Newcastle Feb 1793 sailors; Yarmouth intelligence; seamen's wage petition. HO 42/23 COMPLETE (Dropbox batch 19-23 finished). | HO 42/35_01 (13 Jun-1 Jul 1795) read: Wakefield, Birmingham/Dudley/Bromsgrove, Shardlow requests; Stourbridge, Gloucester, Lewes, Sheffield Place grain-supply letters (no troop requests); Aylesbury/Wisbech? barge riot reported (f.40, civil power sufficed). | HO 42/35_02 (2-13 Jul 1795) read: Essex yeomanry vs food riot (HO42-0060); otherwise grain-supply letters (Stourbridge, Gloucester, Winchester bakers re exports, Bristol, Southampton, Liverpool, Aston Hall/Birmingham corn purchase), Hoddesdon farm servants' wage combination (constables only), Shobdon circular reply. | HO 42/35_03 (13-20 Jul 1795) read: HAC riot-duty offer (HO42-0061); Nottingham JPs ask for grain supply by water (no troops, f.196); Newhaven sufferers' claims for Oxford Militia riot (ff.206-217, context, cf. Bend); Hilperton 'Jacobins hoarding corn'; Privy Council grain engagement replies; Guernsey. | HO 42/35_04 (20-29 Jul 1795) read: Wisbech/Cambridgeshire request via Hardwicke (HO42-0062); Bedford wheat-waggon riot 21 Jul (f.289, magistrate let waggon go, no troops); Barham Downs camp re French officers; grain circulars; Lancaster prisoner calendars. | HO 42/35_05 (29 Jul-7 Aug 1795) read: Wakefield/Knottingley request (HO42-0063); Witney unrequested troops (HO42-0064); Wisbech thanks (added to HO42-0062); Manchester provisions association; Wisbech printed notice; Yarmouth/Plymouth grain; Hampshire sedition. | HO 42/35_06 (7-29 Aug 1795) read: Sheffield volunteers suppress riot / Cameron's regiment removed (HO42-0065); Yorkshire Freeholder Society (Newcastle) libel; Ormskirk grain notice; Fishguard Volunteers acted on magistrates' requisition at Haverfordwest (Wales - not logged); grain/emigrant business. | HO 42/36_01 (Nov 1795) read: no events - county harvest returns (lead added as possible control data). | HO 42/36_02 (Nov 1795) read: Whitby request (HO42-0066); otherwise county harvest returns (Middlesex, Northants, Warwick, Staffs, Oxon, Sussex, Suffolk, Anglesey, Wales, Pembs...). | HO 42/36_03 (Sep-Nov 1795) read: Ely request via Hardwicke (cross-county troop limit); Harewood miners (Other); bread rising near Bristol (f.156, magistrate pacified, no troops); Ashford French prisoners affray - Knatchbull asks their removal (f.214, Kent); Nootka/Vancouver accounts; harvest returns. | HO 42/36_04 (Nov 1795) read: no new events (loyal addresses re Two Acts incl. York internal-defence volunteers' address f.226; Rolvenden (Kent) yeomanry captain offers service after anonymous letter f.258; govt corn to Plymouth/Penzance; Bristol market relief). | HO 42/37_01 (Dec 1795) read: no events (Colchester loyal petition; parish/hundred harvest returns - Notts, Kent, Hants, Northants, Sussex, Isle of Wight etc.). | HO 42/37_04 (Dec 1795) read: Norfolk flour-shipping riots (Wells, Holt) and Townshend coast request; Holt farmers' association; otherwise harvest returns (Notts, Hants, Surrey, Wales, Northumberland, Lincs) and Cambridge college petition. | HO 42/37_02 (Dec 1795) read: no events (harvest returns - Cheshire, Middlesex, Shropshire, Lancashire, Gloucs). | HO 42/37_03 (Dec 1795) read: no events (harvest returns - Lancs, Bucks, Derbys, Essex, Kent, Northumberland, Notts, Dorset/Kent via Duke of Dorset). | HO 42/37_05 (Dec 1795) read: Yarmouth barracks riot by Huntingdon Militia (HO42-0072); Fishguard vessel/butter (Wales, not logged); Huddersfield? loyal meeting reports; Kirkby Stephen/Westmorland; addresses; Hackney Rocks/Gosport association; McMahon memorial; Sudbury/Penrith addresses; Shoreham? - Lanstinan (Wales).
A34: Leads sheet | B34: Events cited by secondary works (Gee, Bend) but NOT yet seen in the original. Move a lead to Events only after reading the document; then set Verified = Y here.
A36: SOURCE SWITCH: HO 40 from 1812 | B36: From 1812 onwards, use HO 40 (Home Office: Disturbances Correspondence) alongside HO 42. Disturbance letters were separated out of HO 42 into HO 40 from 1812 (Bend 2018, ch. 3). Caution: the split was not continuous. Bend finds disturbance letters back in HO 42 for Jul 1813-Jun 1816 and Mar 1818-Jan 1820, so for 1812-1819 check both series. Before 1812, HO 42 only.

Sheet Lookups
A1: Home Sec from (ISO) | B1: Home Secretary | D1: Event type | E1: Key quote? | F1: Folio basis | G1: Image status | H1: Transcription status | I1: Writer role | J1: Disturbance type | K1: Request kind | L1: Civil power inadequate? | M1: Military already nearby? | N1: Outcome | O1: Response source
A2: 1789-06-05 | B2: Grenville | D2: Request for troops | E2: Y | F2: Folio stamp | G2: Digitised (TNA PDF) | H2: Key quote only | I2: Magistrate / JP | J2: Food / provisions | K2: Actual | L2: Y | M2: Y | N2: Approved | O2: HO 42 docket
A3: 1791-06-08 | B3: Dundas | D3: Corps founded | E3: N | F3: PDF page | G3: Own photo taken | H3: Key quote; full text held | I3: Mayor / corporation | J3: Labour / industrial | K3: Pre-emptive | L3: N | M3: N | N3: Denied | O3: HO 43
A4: 1794-07-11 | B4: Portland | D4: Corps armed/expanded | F4: Unclear - check | G4: Needs photo | H4: Full transcription | I4: Lord Lieutenant | J4: Anti-machinery | K4: Contingent | L4: Unclear | M4: Volunteers only | N4: Partly approved | O4: Other
A5: 1801-07-30 | B5: Pelham | D5: Barracks | G5: Not needed | H5: Machine (VLM) draft | I5: Military officer | J5: Election | K5: Report only | M5: Unclear | N5: Forwarded | O5: None found
A6: 1803-08-17 | B6: C. Yorke | D6: Corps forming (context) | H6: VLM checked | I6: Volunteer / militia officer | J6: Radical / political | N6: Not needed
A7: 1804-05-12 | B7: Hawkesbury | D7: Other | I7: Loyalist association | J7: Recruitment / crimping | N7: Unknown
A8: 1806-02-05 | B8: Spencer | I8: MP / peer | J8: Militia ballot
A9: 1807-03-25 | B9: Hawkesbury | I9: Other official | J9: Preventive / general
A10: 1809-11-01 | B10: Ryder | I10: Private individual | J10: Enclosure
A11: 1812-06-11 | B11: Sidmouth | J11: Other / unclear
A12: 1822-01-17 | B12: Peel
A14: Source: standard lists of Secretaries of State for the Home Department (start of term). Context column only.
